Workbook
Name CoreFinancials: 'New Marketecture'!$A$76:$H$139
Name RiskManagement: 'New Marketecture'!$A$250:$F$259
Name Procurement: 'New Marketecture'!$A$260:$H$288
Name AssetsInventory: 'New Marketecture'!$A$162:$H$187
Name Audit: 'New Marketecture'!$A$140:$H$160
Name FinancialInvestments: 'New Marketecture'!$A$248:$H$249
Name PIM: 'New Marketecture'!$A$331:$H$352
Name BudgetPreparation: 'New Marketecture'!$A$26:$H$61
Name SocialBenefits: 'New Marketecture'!$A$290:$H$315
Name PolicyManagement: 'New Marketecture'!$A$8:$H$25
Name Treasury: 'New Marketecture'!$A$196:$H$217
Name Grants: 'New Marketecture'!$A$316:$H$330
Name HR: 'New Marketecture'!$A$493:$H$570
Name Tax: 'New Marketecture'!$A$389:$H$449
Name Payroll: 'New Marketecture'!$A$464:$H$492
Name PerformanceTransparency: 'New Marketecture'!$A$62:$H$75
Name PBHC: 'New Marketecture'!$A$450:$H$463
Name Revenue: 'New Marketecture'!$A$346:$H$389
Name Debt: 'New Marketecture'!$A$218:$H$247

Sheet Read Me
A1: Public Financial Management Component Map
A2: Read Me
A3: Purpose
A4: • identify all possible public finance functions & associated non-financial functions (i.e. budget - policy, payroll - HR)
A5: • use the component business mapping technique
A6: • inform the FreeBalance product marketecture
A7: PFM CM Sheets
A8: PFM Component Map: Breakdown from pillar through function to component
A9: New Marketecture: Maps new product marketecture to PFMCM functions
A10: Concepts: Explains the component business mapping technique with FreeBalanc extensions
A11: Pivot Table: Analysis of components and pillars
A12: Supporting Material
... A36: Red for all transparency components that begin with X.X.T1

Sheet PFM Component Map
B1: FreeBalance Public Financial Management Component Map 4.3, 2026
A2: Pillar | B2: Function | C2: Component | D2: Type | E2: Description | F2: Public Finance Purpose | G2: =Concepts!F4 -> Activities | H2: =Concepts!F5 -> Resources | I2: =Concepts!F6 -> Governance | J2: =Concepts!F7 -> Business Services
A3: 1. Government Performance Management | B3: 1.1 Policy Management | C3: 1.1.01 Legislation Management | D3: D-RM | E3: =if(D3<>"",VLOOKUP(D3,Concepts!C$2:D$12,2,FALSE),"") -> Reform & Modernization | F3: Develop and manage internal government public finance legislation. | J3: • From: actuals, trends, previous plans, 1.1.2, 1.1.4 • To:
A4: 1. Government Performance Management | B4: 1.1 Policy Management | C4: 1.1.02 Regulation Management | D4: D-RM | E4: =if(D4<>"",VLOOKUP(D4,Concepts!C$2:D$12,2,FALSE),"") -> Reform & Modernization | F4: Develop and manage external to government regulatory environment in support of public finance objectives.
A5: 1. Government Performance Management | B5: 1.1 Policy Management | C5: 1.1.03 Development Strategy & Government Goals | D5: D-PS | E5: =if(D5<>"",VLOOKUP(D5,Concepts!C$2:D$12,2,FALSE),"") -> Planning & Scenarios | F5: Articulate government goals like national development strategies, SDGs, long-term visions and 5 year plans | G5: National plans, political platforms, budget priorities, scenario analysis | H5: Executive, planning & economic departments, budget offices, political parties, parliaments, IFIs, outreach
A6: 1. Government Performance Management | B6: 1.1 Policy Management | C6: 1.1.04 Policy Legal Framework | D6: D-RM | E6: =if(D6<>"",VLOOKUP(D6,Concepts!C$2:D$12,2,FALSE),"") -> Reform & Modernization | F6: Integrate planning with policy objectives, and legal framework | J6: • From: • To:
A7: 1. Government Performance Management | B7: 1.1 Policy Management | C7: 1.1.05 Intergovernmental Fiscal Relations | D7: D-PS | E7: =if(D7<>"",VLOOKUP(D7,Concepts!C$2:D$12,2,FALSE),"") -> Planning & Scenarios | F7: Support for fiscal relations in planning for independent agencies, sub-national governments, and SOEs | J7: • From: • To:
A8: 1. Government Performance Management | B8: 1.1 Policy Management | C8: 1.1.06 Fiscal Framework | D8: C- GC | E8: =if(D8<>"",VLOOKUP(D8,Concepts!C$2:D$12,2,FALSE),"") -> Government Controls | F8: Integrate fiscal rules & procedures in policy & budget planning.
A9: 1. Government Performance Management | B9: 1.1 Policy Management | C9: 1.1.07 Trend Analysis | D9: D-PS | E9: =if(D9<>"",VLOOKUP(D9,Concepts!C$2:D$12,2,FALSE),"") -> Planning & Scenarios | F9: Enable statistical analysis of government & economic data over time
A10: 1. Government Performance Management | B10: 1.1 Policy Management | C10: 1.1.08 Macroeconomic Forecasting | D10: D-PS | E10: =if(D10<>"",VLOOKUP(D10,Concepts!C$2:D$12,2,FALSE),"") -> Planning & Scenarios | F10: Predict potential revenue mobilization, including effects of government spending and regulations, as input to budget preparation
A11: 1. Government Performance Management | B11: 1.1 Policy Management | C11: 1.1.09 Policy Planning Versions | D11: D-PS | E11: =if(D11<>"",VLOOKUP(D11,Concepts!C$2:D$12,2,FALSE),"") -> Planning & Scenarios | F11: Support stages of policy formulation, including internal papers and reports, as input to budget planning | J11: • From: • To:
A12: 1. Government Performance Management | B12: 1.1 Policy Management | C12: 1.1.10 Policy Impact Assessment | D12: D-PS | E12: =if(D12<>"",VLOOKUP(D12,Concepts!C$2:D$12,2,FALSE),"") -> Planning & Scenarios | F12: Evaluate proposed policies for social, economic, and environmental impacts using evidence-based methodologies and scenario modeling.
A13: 1. Government Performance Management | B13: 1.1 Policy Management | C13: 1.1.11 Cross-Sectoral Policy Integration | D13: D-PS | E13: =if(D13<>"",VLOOKUP(D13,Concepts!C$2:D$12,2,FALSE),"") -> Planning & Scenarios | F13: Ensure coherence across government policies, such as climate, social protection, and economic development, to align with overarching strategic goals
A14: 1. Government Performance Management | B14: 1.1 Policy Management | C14: 1.1.12 International Commitments & Agreements | D14: C- GC | E14: =if(D14<>"",VLOOKUP(D14,Concepts!C$2:D$12,2,FALSE),"") -> Government Controls | F14: Monitor and integrate international policy commitments (e.g., SDGs, Paris Agreement, WTO obligations) into national policy planning frameworks
A15: 1. Government Performance Management | B15: 1.1 Policy Management | C15: 1.1.13 Evidence-Based Policy Evaluation | D15: C- GC | E15: =if(D15<>"",VLOOKUP(D15,Concepts!C$2:D$12,2,FALSE),"") -> Government Controls | F15: Facilitate policy impact assessments and program evaluations using empirical data to measure effectiveness and inform decision-making.
A16: 1. Government Performance Management | B16: 1.1 Policy Management | C16: 1.1.14 Public Sector Efficiency & Productivity Metrics | D16: D-PS | E16: =if(D16<>"",VLOOKUP(D16,Concepts!C$2:D$12,2,FALSE),"") -> Planning & Scenarios | F16: Identify efficiency indicators, such as cost-effectiveness, timeliness, and resource utilization, to optimize public service delivery.
A17: 1. Government Performance Management | B17: 1.1 Policy Management | C17: 1.1.A1 Policy Approvals | D17: D-AP | E17: =if(D17<>"",VLOOKUP(D17,Concepts!C$2:D$12,2,FALSE),"") -> Approvals | F17: Support policy approvals that feed into budget planning.
A18: 1. Government Performance Management | B18: 1.1 Policy Management | C18: 1.1.T1 Stakeholder Consultation & Engagement | D18: E-FT | E18: =if(D18<>"",VLOOKUP(D18,Concepts!C$2:D$12,2,FALSE),"") -> Fiscal Transparency | F18: Facilitate structured engagement with civil society, private sector, development partners, and other stakeholders to ensure inclusive policy planning. Support surveys.
A19: 1. Government Performance Management | B19: 1.1 Policy Management | C19: 1.1.T2 Policy Transparency | D19: E-FT | E19: =if(D19<>"",VLOOKUP(D19,Concepts!C$2:D$12,2,FALSE),"") -> Fiscal Transparency | F19: Support publishing of policy documents, policy information, government goals, and national development strategies
A20: 1. Government Performance Management | B20: 1.1 Policy Management | C20: 1.1.T3 Economics Transparency | D20: E-FT | E20: =if(D20<>"",VLOOKUP(D20,Concepts!C$2:D$12,2,FALSE),"") -> Fiscal Transparency | F20: Support publishing of macroeconomic analysis, fiscal assumptions, budget envelopes
A21: 1. Government Performance Management | B21: 1.2 Budget Planning / Formulation | C21: 1.2.01 Budget Legal Framework | D21: D-RM | E21: =if(D21<>"",VLOOKUP(D21,Concepts!C$2:D$12,2,FALSE),"") -> Reform & Modernization | F21: Support the legal structure, processes, fiscal rules, and schedules for budget preparation | J21: • From: • To:
A22: 1. Government Performance Management | B22: 1.2 Budget Planning / Formulation | C22: 1.2.02 Budget Circular & Budget Ceilings | D22: C- GC | E22: =if(D22<>"",VLOOKUP(D22,Concepts!C$2:D$12,2,FALSE),"") -> Government Controls | F22: Provide guidance in the development of MDA budgets, including schedule and ceilings control | J22: • From: • To:
A23: 1. Government Performance Management | B23: 1.2 Budget Planning / Formulation | C23: 1.2.03 Multiple Year Budget Formulation | D23: D-PS | E23: =if(D23<>"",VLOOKUP(D23,Concepts!C$2:D$12,2,FALSE),"") -> Planning & Scenarios | F23: Prepare 3 to 5 year budgets to coordinate spending priorities, manage multiple-year investments, and determine results. | J23: • From: • To:
A24: 1. Government Performance Management | B24: 1.2 Budget Planning / Formulation | C24: 1.2.04 Budget Planning Monitoring | D24: C-ME | E24: =if(D24<>"",VLOOKUP(D24,Concepts!C$2:D$12,2,FALSE),"") -> Monitoring & Evaluation | F24: Enable monitoring the progress of MDA budgets during formulation to provide guidance
A25: 1. Government Performance Management | B25: 1.2 Budget Planning / Formulation | C25: 1.2.05 Cost Assumptions | D25: C- GC | E25: =if(D25<>"",VLOOKUP(D25,Concepts!C$2:D$12,2,FALSE),"") -> Government Controls | F25: Leverage cost drivers and cost driver packages for more accurate projections | J25: • From: • To:
A26: 1. Government Performance Management | B26: 1.2 Budget Planning / Formulation | C26: 1.2.06 Scenario Planning | D26: D-PS | E26: =if(D26<>"",VLOOKUP(D26,Concepts!C$2:D$12,2,FALSE),"") -> Planning & Scenarios | F26: Provide forecasting and scenarios to improve budget credibility, and enable re-forecasting during budget implementation | J26: • From: • To:
A27: 1. Government Performance Management | B27: 1.2 Budget Planning / Formulation | C27: 1.2.07 Budget Calendar, Versions | D27: C- GC | E27: =if(D27<>"",VLOOKUP(D27,Concepts!C$2:D$12,2,FALSE),"") -> Government Controls | F27: Manage the budget calendar with version controls across the budget planning cycle | J27: • From: • To:
A28: 1. Government Performance Management | B28: 1.2 Budget Planning / Formulation | C28: 1.2.08 Budget Releases Rules | D28: C- GC | E28: =if(D28<>"",VLOOKUP(D28,Concepts!C$2:D$12,2,FALSE),"") -> Government Controls | F28: Support for partial budget releases when the budget is not approved or partly approved
A29: 1. Government Performance Management | B29: 1.2 Budget Planning / Formulation | C29: 1.2.09 Capital & Recurrent Expenditure Planning | D29: D-PS | E29: =if(D29<>"",VLOOKUP(D29,Concepts!C$2:D$12,2,FALSE),"") -> Planning & Scenarios | F29: Differentiate planning for capital investments and recurrent expenditures, ensuring alignment with fiscal sustainability and public investment strategies.
A30: 1. Government Performance Management | B30: 1.2 Budget Planning / Formulation | C30: 1.2.10 Climate & Sustainability Budgeting | D30: D-PS | E30: =if(D30<>"",VLOOKUP(D30,Concepts!C$2:D$12,2,FALSE),"") -> Planning & Scenarios | F30: Embed climate-responsive budgeting and sustainable development considerations into budget formulation to track green spending and adaptation investments.
A31: 1. Government Performance Management | B31: 1.2 Budget Planning / Formulation | C31: 1.2.11 Gender, Wellbeing & Social Inclusion Budgeting | D31: D-PS | E31: =if(D31<>"",VLOOKUP(D31,Concepts!C$2:D$12,2,FALSE),"") -> Planning & Scenarios | F31: Incorporate gender-responsive and inclusive budgeting methodologies to address social equity, poverty reduction, and support for vulnerable groups.
A32: 1. Government Performance Management | B32: 1.2 Budget Planning / Formulation | C32: 1.2.12 Contingency & Emergency Budget Planning | D32: D-PS | E32: =if(D32<>"",VLOOKUP(D32,Concepts!C$2:D$12,2,FALSE),"") -> Planning & Scenarios | F32: Allocate budgetary provisions for emergency response, economic shocks, and unforeseen expenditures within fiscal limits.
A33: 1. Government Performance Management | B33: 1.2 Budget Planning / Formulation | C33: 1.2.13 Development Partner & Donor Coordination | D33: D-PS | E33: =if(D33<>"",VLOOKUP(D33,Concepts!C$2:D$12,2,FALSE),"") -> Planning & Scenarios | F33: Integrate external financing, donor funds, and project support into budget formulation, ensuring alignment with national priorities and fiscal strategies.
A34: 1. Government Performance Management | B34: 1.2 Budget Planning / Formulation | C34: 1.2.14 Subnational & Intergovernmental Budgeting | D34: D-PS | E34: =if(D34<>"",VLOOKUP(D34,Concepts!C$2:D$12,2,FALSE),"") -> Planning & Scenarios | F34: Support budgeting for subnational governments and intergovernmental transfers, ensuring consistency with national fiscal policies and revenue-sharing mechanisms.
A35: 1. Government Performance Management | B35: 1.2 Budget Planning / Formulation | C35: 1.2.15 Cost-Benefit Analysis | D35: D-PS | E35: =if(D35<>"",VLOOKUP(D35,Concepts!C$2:D$12,2,FALSE),"") -> Planning & Scenarios | F35: Facilitate economic analysis of government projects, including cost-benefit analysis, return on investment (ROI), and value-for-money assessments.
A36: 1. Government Performance Management | B36: 1.2 Budget Planning / Formulation | C36: 1.2.16 PEFA Assessments | D36: C-OA | E36: =if(D36<>"",VLOOKUP(D36,Concepts!C$2:D$12,2,FALSE),"") -> Oversight & Audit | F36: Undergo Public Expenditure and Financial Accountability Assessment (PEFA) , especially PI-14 to PI-18
A37: 1. Government Performance Management | B37: 1.2 Budget Planning / Formulation | C37: 1.2.A1 Intermediate Budget Approvals | D37: D-AP | E37: =if(D37<>"",VLOOKUP(D37,Concepts!C$2:D$12,2,FALSE),"") -> Approvals | F37: Approve intermediate budgets such as division, department, ministry, and budget office prior to legislative approval
A38: 1. Government Performance Management | B38: 1.2 Budget Planning / Formulation | C38: 1.2.A2 Organic Budget Law / Vote | D38: D-AP | E38: =if(D38<>"",VLOOKUP(D38,Concepts!C$2:D$12,2,FALSE),"") -> Approvals | F38: Approve the budget for implementation after executive and legislative approval | J38: • From: • To:
A39: 1. Government Performance Management | B39: 1.2 Budget Planning / Formulation | C39: 1.2.A2 Partial Budget Release | D39: D-AP | E39: =if(D39<>"",VLOOKUP(D39,Concepts!C$2:D$12,2,FALSE),"") -> Approvals | F39: Approve partial releases complying with budget laws that requires executive and/or legislative approval
A40: 1. Government Performance Management | B40: 1.2 Budget Planning / Formulation | C40: 1.2.T1 Budget Books | D40: E-FT | E40: =if(D40<>"",VLOOKUP(D40,Concepts!C$2:D$12,2,FALSE),"") -> Fiscal Transparency | F40: Create budget documents, citizen budgets, pamphlets and other formatted output | J40: • From: • To:
A41: 1. Government Performance Management | B41: 1.2 Budget Planning / Formulation | C41: 1.2.T2 E-Budget Preparation Transparency | D41: E-FT | E41: =if(D41<>"",VLOOKUP(D41,Concepts!C$2:D$12,2,FALSE),"") -> Fiscal Transparency | F41: Support online budget formulation transparency, including open data support
A42: 1. Government Performance Management | B42: 1.2 Budget Planning / Formulation | C42: 1.2.T3 Public Consultation & Transparency in Budgeting | D42: E-FT | E42: =if(D42<>"",VLOOKUP(D42,Concepts!C$2:D$12,2,FALSE),"") -> Fiscal Transparency | F42: Facilitate public engagement & feedback in budget formulation, including citizen input, participatory budgeting initiatives, and transparent publication of budget drafts. Support surveys.
A43: 1. Government Performance Management | B43: 1.3 Public Accounts Management | C43: 1.3.01 Accounting Regulatory Framework | D43: C- GC | E43: =if(D43<>"",VLOOKUP(D43,Concepts!C$2:D$12,2,FALSE),"") -> Government Controls | F43: Articulate government accounting regulatory & conceptual framework
A44: 1. Government Performance Management | B44: 1.3 Public Accounts Management | C44: 1.3.02 Accounting Policies | D44: C- GC | E44: =if(D44<>"",VLOOKUP(D44,Concepts!C$2:D$12,2,FALSE),"") -> Government Controls | F44: Articulate government accounting policies including: use of estimates, dealing with errors, reporting events after reporting date
A45: 1. Government Performance Management | B45: 1.3 Public Accounts Management | C45: 1.3.03 Accounting Codes in Chart of Accounts | D45: D-RM | E45: =if(D45<>"",VLOOKUP(D45,Concepts!C$2:D$12,2,FALSE),"") -> Reform & Modernization | F45: Ensure that accounting codes are in the Chart of Accounts | J45: • From: • To:
A46: 1. Government Performance Management | B46: 1.3 Public Accounts Management | C46: 1.3.04 Budget Classifications in Chart of Accounts | D46: D-RM | E46: =if(D46<>"",VLOOKUP(D46,Concepts!C$2:D$12,2,FALSE),"") -> Reform & Modernization | F46: Ensure that budget classifications are also integrated in the Chart of Accounts | J46: • From: • To:
A47: 1. Government Performance Management | B47: 1.3 Public Accounts Management | C47: 1.3.05 Program Classifications in Chart of Accounts | D47: D-RM | E47: =if(D47<>"",VLOOKUP(D47,Concepts!C$2:D$12,2,FALSE),"") -> Reform & Modernization | F47: Provide program classifications for program management in the Chart of Accounts | J47: • From: • To:
A48: 1. Government Performance Management | B48: 1.3 Public Accounts Management | C48: 1.3.06 National Standards in Chart of Accounts | D48: D-RM | E48: =if(D48<>"",VLOOKUP(D48,Concepts!C$2:D$12,2,FALSE),"") -> Reform & Modernization | F48: Ensure that national accounting standards are supported in the Chart of Accounts such as: GASB, GAAP | J48: • From: • To:
A49: 1. Government Performance Management | B49: 1.3 Public Accounts Management | C49: 1.3.07 International Standards in Chart of Accounts | D49: D-RM | E49: =if(D49<>"",VLOOKUP(D49,Concepts!C$2:D$12,2,FALSE),"") -> Reform & Modernization | F49: Ensure that international standards are supported in the Chart of Accounts such as: GFS, COFOG, IPSAS
A50: 1. Government Performance Management | B50: 1.3 Public Accounts Management | C50: 1.3.08 Sustainable Development Goals in Chart of Accounts | D50: D-RM | E50: =if(D50<>"",VLOOKUP(D50,Concepts!C$2:D$12,2,FALSE),"") -> Reform & Modernization | F50: Embed sustainable development into the Chart of Accounts
A51: 1. Government Performance Management | B51: 1.3 Public Accounts Management | C51: 1.3.09 Gender, Wellbeing and Inclusion in Chart of Accounts | D51: D-RM | E51: =if(D51<>"",VLOOKUP(D51,Concepts!C$2:D$12,2,FALSE),"") -> Reform & Modernization | F51: Embed wellbeing, gender, inclusion etc. into the Chart of Accounts
A52: 1. Government Performance Management | B52: 1.3 Public Accounts Management | C52: 1.3.10 Reporting Objects | D52: D-RM | E52: =if(D52<>"",VLOOKUP(D52,Concepts!C$2:D$12,2,FALSE),"") -> Reform & Modernization | F52: Ability to create alternative roll-ups or side concepts to show detailed CoA data in different reporting configurations.
A53: 1. Government Performance Management | B53: 1.3 Public Accounts Management | C53: 1.3.11 PEFA Assessments | D53: C-OA | E53: =if(D53<>"",VLOOKUP(D53,Concepts!C$2:D$12,2,FALSE),"") -> Oversight & Audit | F53: Undergo Public Expenditure and Financial Accountability Assessment (PEFA) , especially PI-4
A54: 1. Government Performance Management | B54: 1.3 Public Accounts Management | C54: 1.3.A1 Chart of Accounts Additions | D54: D-AP | E54: =if(D54<>"",VLOOKUP(D54,Concepts!C$2:D$12,2,FALSE),"") -> Approvals | F54: Support the addition of Chart of Accounts elements without affecting the structure
A55: 1. Government Performance Management | B55: 1.3 Public Accounts Management | C55: 1.3.A2 Multiple-Year Chart of Accounts | D55: D-AP | E55: =if(D55<>"",VLOOKUP(D55,Concepts!C$2:D$12,2,FALSE),"") -> Approvals | F55: Update Charts of Accounts across fiscal years, including support of viewing data from the year CoA with a different year CoA.
A56: 1. Government Performance Management | B56: 1.3 Public Accounts Management | C56: 1.3.T1 Government Classification Transparency | D56: E-FT | E56: =if(D56<>"",VLOOKUP(D56,Concepts!C$2:D$12,2,FALSE),"") -> Fiscal Transparency | F56: Support the exposure of government classifications in reports and open data.
A57: 1. Government Performance Management | B57: 1.4 Performance Structures & Implementation | C57: 1.4.01 Output Performance Indicators / Targets | D57: C-PM | E57: =if(D57<>"",VLOOKUP(D57,Concepts!C$2:D$12,2,FALSE),"") -> Performance Management | F57: Identify output and outcome targets in a Chart of Goals | J57: • From: • To:
A58: 1. Government Performance Management | B58: 1.4 Performance Structures & Implementation | C58: 1.4.02 Chart of Goals integrated with Chart of Accounts | D58: C-PM | E58: =if(D58<>"",VLOOKUP(D58,Concepts!C$2:D$12,2,FALSE),"") -> Performance Management | F58: Integrate Chart of Goals with Chart of Accounts and support performance schemes like balanced scorecard, KPIs, and OKRs | J58: • From: • To:
A59: 1. Government Performance Management | B59: 1.4 Performance Structures & Implementation | C59: 1.4.03 Public Finance Analytics | D59: C-PM | E59: =if(D59<>"",VLOOKUP(D59,Concepts!C$2:D$12,2,FALSE),"") -> Performance Management | F59: Analytics, big data analytics (including data from outside the financial system), statistics, data science and machine learning
A60: 1. Government Performance Management | B60: 1.4 Performance Structures & Implementation | C60: 1.4.04 Public Finance Visualization | D60: C-PM | E60: =if(D60<>"",VLOOKUP(D60,Concepts!C$2:D$12,2,FALSE),"") -> Performance Management | F60: Visualization of public finance information including charts, graphs, animations, and geographic presentation with drill-down and drill-through
A61: 1. Government Performance Management | B61: 1.4 Performance Structures & Implementation | C61: 1.4.05 Performance Presentation | D61: C-ME | E61: =if(D61<>"",VLOOKUP(D61,Concepts!C$2:D$12,2,FALSE),"") -> Monitoring & Evaluation | F61: Support performance dashboards, scorecards, and reporting including: balanced scorecard, key performance indicator, and objectives and key results methods
A62: 1. Government Performance Management | B62: 1.4 Performance Structures & Implementation | C62: 1.4.06 Public Finance Storytelling | D62: C-PM | E62: =if(D62<>"",VLOOKUP(D62,Concepts!C$2:D$12,2,FALSE),"") -> Performance Management | F62: Enable storytelling through integrated numerous visualization techniques, text, and video to tell stories
A63: 1. Government Performance Management | B63: 1.4 Performance Structures & Implementation | C63: 1.4.07 Spending Reviews | D63: C-OA | E63: =if(D63<>"",VLOOKUP(D63,Concepts!C$2:D$12,2,FALSE),"") -> Oversight & Audit | F63: Support periodic mechanisms for performance oversight
A64: 1. Government Performance Management | B64: 1.4 Performance Structures & Implementation | C64: 1.4.08 Peer Benchmarking & Global Comparisons | D64: C-PM | E64: =if(D64<>"",VLOOKUP(D64,Concepts!C$2:D$12,2,FALSE),"") -> Performance Management | F64: Compare public sector performance indicators against regional, national, and international benchmarks (e.g., IMF, OECD, World Bank data).
A65: 1. Government Performance Management | B65: 1.4 Performance Structures & Implementation | C65: 1.4.08 Monitoring & Evaluation (M&E) Frameworks | D65: C-ME | E65: =if(D65<>"",VLOOKUP(D65,Concepts!C$2:D$12,2,FALSE),"") -> Monitoring & Evaluation | F65: Define key performance indicators, tracking mechanisms, and reporting structures to assess policy effectiveness and improve decision-making.
A66: 1. Government Performance Management | B66: 1.4 Performance Structures & Implementation | C66: 1.4.09 PEFA Assessments | D66: C-OA | E66: =if(D66<>"",VLOOKUP(D66,Concepts!C$2:D$12,2,FALSE),"") -> Oversight & Audit | F66: Undergo Public Expenditure and Financial Accountability Assessment (PEFA) , especially PI-8.
A67: 1. Government Performance Management | B67: 1.4 Performance Structures & Implementation | C67: 1.4.A1 Chart of Goals Additions | D67: D-AP | E67: =if(D67<>"",VLOOKUP(D67,Concepts!C$2:D$12,2,FALSE),"") -> Approvals | F67: Support the addition of Chart of Goals elements without affecting the structure
A68: 1. Government Performance Management | B68: 1.4 Performance Structures & Implementation | C68: 1.4.A2 Multiple-Year Chart of Goals | D68: D-AP | E68: =if(D68<>"",VLOOKUP(D68,Concepts!C$2:D$12,2,FALSE),"") -> Approvals | F68: Update Charts of Goals across fiscal years
A69: 1. Government Performance Management | B69: 1.4 Performance Structures & Implementation | C69: 1.4.T1 E-Performance Transparency | D69: E-FT | E69: =if(D69<>"",VLOOKUP(D69,Concepts!C$2:D$12,2,FALSE),"") -> Fiscal Transparency | F69: Support a performance transparency portal
A70: 2. Government Compliance Management | B70: 2.1 Budget and Appropriation Control | C70: 2.1.01 Budget Controls | D70: C- GC | E70: =if(D70<>"",VLOOKUP(D70,Concepts!C$2:D$12,2,FALSE),"") -> Government Controls | F70: Enable multiple line item and aggregate budget controls for differing periods with differing rules, includes multiple currencies | J70: • From: • To:
A71: 2. Government Compliance Management | B71: 2.1 Budget and Appropriation Control | C71: 2.1.02 Financial Regulations | D71: C- GC | E71: =if(D71<>"",VLOOKUP(D71,Concepts!C$2:D$12,2,FALSE),"") -> Government Controls | F71: Support fiscal regulation rules and workflow across the budget cycle | J71: • From: • To:
A72: 2. Government Compliance Management | B72: 2.1 Budget and Appropriation Control | C72: 2.1.03 Appropriations & Warrants | D72: C- GC | E72: =if(D72<>"",VLOOKUP(D72,Concepts!C$2:D$12,2,FALSE),"") -> Government Controls | F72: Enable release of spending authorization to MDAs | J72: • From: • To:
A73: 2. Government Compliance Management | B73: 2.1 Budget and Appropriation Control | C73: 2.1.04 Fiscal Rules | D73: C- GC | E73: =if(D73<>"",VLOOKUP(D73,Concepts!C$2:D$12,2,FALSE),"") -> Government Controls | F73: Embed fiscal rules in budget planning
A74: 2. Government Compliance Management | B74: 2.1 Budget and Appropriation Control | C74: 2.1.05 Segregation of Duties | D74: C- GC | E74: =if(D74<>"",VLOOKUP(D74,Concepts!C$2:D$12,2,FALSE),"") -> Government Controls | F74: Ensure segregation of duties across budget cycles
A75: 2. Government Compliance Management | B75: 2.1 Budget and Appropriation Control | C75: 2.1.06 Budget Requests | D75: E-PE | E75: =if(D75<>"",VLOOKUP(D75,Concepts!C$2:D$12,2,FALSE),"") -> Process Execution | F75: Ensure segregation of duties across budget cycles
A76: 2. Government Compliance Management | B76: 2.1 Budget and Appropriation Control | C76: 2.1.A1 Budget and Appropriation Approvals | D76: D-AP | E76: =if(D76<>"",VLOOKUP(D76,Concepts!C$2:D$12,2,FALSE),"") -> Approvals | F76: Provide workflow for approvals, following rules like segregation of duties and more senior approvals based on rules for confirming budgets and appropriations
A77: 2. Government Compliance Management | B77: 2.1 Budget and Appropriation Control | C77: 2.1.T1 Initial Budget Transparency | D77: E-FT | E77: =if(D77<>"",VLOOKUP(D77,Concepts!C$2:D$12,2,FALSE),"") -> Fiscal Transparency | F77: Capturing for reports and open data of the initial budget and appropriation amounts.
A78: 2. Government Compliance Management | B78: 2.2 Commitment Management | C78: 2.2.01 Commitments | D78: C- GC | E78: =if(D78<>"",VLOOKUP(D78,Concepts!C$2:D$12,2,FALSE),"") -> Government Controls | F78: Manage commitments (soft commitments, pre-encumbrances) at the purchase requisition stage integrated with budget controls, including de-commitments | J78: • From: • To:
A79: 2. Government Compliance Management | B79: 2.2 Commitment Management | C79: 2.2.02 Obligations | D79: C- GC | E79: =if(D79<>"",VLOOKUP(D79,Concepts!C$2:D$12,2,FALSE),"") -> Government Controls | F79: Manage obligations (hard commitments, encumbrances) at the purchase order/contract stage aligned with budget controls, including de-obligations | J79: • From: • To:
A80: 2. Government Compliance Management | B80: 2.2 Commitment Management | C80: 2.2.03 Multiple-Year Commitments | D80: C- GC | E80: =if(D80<>"",VLOOKUP(D80,Concepts!C$2:D$12,2,FALSE),"") -> Government Controls | F80: Support contractual requirements for commitments to following fiscal years with roll-over rules | J80: • From: • To:
A81: 2. Government Compliance Management | B81: 2.2 Commitment Management | C81: 2.2.04 Multiple-Year Obligations | D81: C- GC | E81: =if(D81<>"",VLOOKUP(D81,Concepts!C$2:D$12,2,FALSE),"") -> Government Controls | F81: Support entitlement obligations to following fiscal years with rollover rules | J81: • From: • To:
A82: 2. Government Compliance Management | B82: 2.2 Commitment Management | C82: 2.2.05 Donor & External Funding Appropriation Control | D82: C- GC | E82: =if(D82<>"",VLOOKUP(D82,Concepts!C$2:D$12,2,FALSE),"") -> Government Controls | F82: Track donor-funded budgets, ensuring alignment with government financial regulations and integration with core public finance systems.
A83: 2. Government Compliance Management | B83: 2.2 Commitment Management | C83: 2.2.06 Liquidity-Based Controls | D83: C- GC | E83: =if(D83<>"",VLOOKUP(D83,Concepts!C$2:D$12,2,FALSE),"") -> Government Controls | F83: Support liquidity-based and cash-based controls to constrain commitments.
A84: 2. Government Compliance Management | B84: 2.2 Commitment Management | C84: 2.2.07 PEFA Assessments | D84: C-OA | E84: =if(D84<>"",VLOOKUP(D84,Concepts!C$2:D$12,2,FALSE),"") -> Oversight & Audit | F84: Undergo Public Expenditure and Financial Accountability Assessment (PEFA) , especially PI-21 & PI-22
A85: 2. Government Compliance Management | B85: 2.2 Commitment Management | C85: 2.2.A1 Commitment and Obligations Approvals | D85: D-AP | E85: =if(D85<>"",VLOOKUP(D85,Concepts!C$2:D$12,2,FALSE),"") -> Approvals | F85: Provide workflow for approvals, following rules like segregation of duties and more senior approvals based on rules
A86: 2. Government Compliance Management | B86: 2.2 Commitment Management | C86: 2.1.T1 In-progress Budget Transparency | D86: E-FT | E86: =if(D86<>"",VLOOKUP(D86,Concepts!C$2:D$12,2,FALSE),"") -> Fiscal Transparency | F86: Capturing in-progress commitments and obligations for exports and open data.
A87: 2. Government Compliance Management | B87: 2.3 Budget Execution | C87: 2.3.01 Execution Rules | D87: C- GC | E87: =if(D87<>"",VLOOKUP(D87,Concepts!C$2:D$12,2,FALSE),"") -> Government Controls | F87: Support fiscal rules for adapting budgets during the fiscal years from departmental capabilities to legislative approval depending on Chart of Accounts classifications
A88: 2. Government Compliance Management | B88: 2.3 Budget Execution | C88: 2.3.02 Supplemental Budgets | D88: E-PE | E88: =if(D88<>"",VLOOKUP(D88,Concepts!C$2:D$12,2,FALSE),"") -> Process Execution | F88: Enable the creation of net-new supplemental budgets that are reflected in budget controls | J88: • From: • To:
A89: 2. Government Compliance Management | B89: 2.3 Budget Execution | C89: 2.3.03 Budget Transfers & Virements | D89: E-PE | E89: =if(D89<>"",VLOOKUP(D89,Concepts!C$2:D$12,2,FALSE),"") -> Process Execution | F89: Enable controlled reallocations within the budget framework, ensuring compliance with financial regulations and approval workflows. | J89: • From: • To:
A90: 2. Government Compliance Management | B90: 2.3 Budget Execution | C90: 2.3.04 Free Balance | D90: C-ME | E90: =if(D90<>"",VLOOKUP(D90,Concepts!C$2:D$12,2,FALSE),"") -> Monitoring & Evaluation | F90: Identify available budgets to spend (the "free balance") | J90: • From: • To:
A91: 2. Government Compliance Management | B91: 2.3 Budget Execution | C91: 2.3.05 Variances and Forecasting | D91: C-ME | E91: =if(D91<>"",VLOOKUP(D91,Concepts!C$2:D$12,2,FALSE),"") -> Monitoring & Evaluation | F91: Show spending vs. budget plan variance, and forecast potential surplus or deficit situations to adjust spending
A92: 2. Government Compliance Management | B92: 2.3 Budget Execution | C92: 2.3.06 Budget Execution Tracking | D92: C-ME | E92: =if(D92<>"",VLOOKUP(D92,Concepts!C$2:D$12,2,FALSE),"") -> Monitoring & Evaluation | F92: Enable real-time tracking of actual expenditures against appropriated funds to enhance accountability and prevent budget overruns.
A93: 2. Government Compliance Management | B93: 2.3 Budget Execution | C93: 2.3.07 Contingency Fund & Emergency Appropriations | D93: E-PE | E93: =if(D93<>"",VLOOKUP(D93,Concepts!C$2:D$12,2,FALSE),"") -> Process Execution | F93: Manage contingency reserves and emergency spending approvals within fiscal discipline frameworks.
A94: 2. Government Compliance Management | B94: 2.3 Budget Execution | C94: 2.3.08 Performance-Linked Budget Execution | D94: C-PM | E94: =if(D94<>"",VLOOKUP(D94,Concepts!C$2:D$12,2,FALSE),"") -> Performance Management | F94: Link budget appropriations to performance results, ensuring that spending aligns with policy objectives and expected outcomes.
A95: 2. Government Compliance Management | B95: 2.3 Budget Execution | C95: 2.3.09 PEFA Assessments | D95: C-OA | E95: =if(D95<>"",VLOOKUP(D95,Concepts!C$2:D$12,2,FALSE),"") -> Oversight & Audit | F95: Undergo Public Expenditure and Financial Accountability Assessment (PEFA) , especially PI-1 & PI-2
A96: 2. Government Compliance Management | B96: 2.3 Budget Execution | C96: 2.3.A1 Budget Execution Approvals | D96: D-AP | E96: =if(D96<>"",VLOOKUP(D96,Concepts!C$2:D$12,2,FALSE),"") -> Approvals | F96: Approval process for budget transfers, virements, and supplemental budgets based on rules, including escalation to legislatures.
A97: 2. Government Compliance Management | B97: 2.3 Budget Execution | C97: 2.3.T1 Budget Execution Transparency | D97: E-FT | E97: =if(D97<>"",VLOOKUP(D97,Concepts!C$2:D$12,2,FALSE),"") -> Fiscal Transparency | F97: Transparency of budget changes: actuals, variances, transfers, including support for open data
A98: 2. Government Compliance Management | B98: 2.4 Compliance and Governance | C98: 2.4.01 Organizational Structures | D98: C- GC | E98: =if(D98<>"",VLOOKUP(D98,Concepts!C$2:D$12,2,FALSE),"") -> Government Controls | F98: Articulation of government organization structures to support workflow, business rules, escalation, segregation of duties for compliance
A99: 2. Government Compliance Management | B99: 2.4 Compliance and Governance | C99: 2.4.02 Regulatory Compliance | D99: C- GC | E99: =if(D99<>"",VLOOKUP(D99,Concepts!C$2:D$12,2,FALSE),"") -> Government Controls | F99: Support for regulations that impact public finance like privacy, accessibility, and diversity
A100: 2. Government Compliance Management | B100: 2.4 Compliance and Governance | C100: 2.4.03 Process Development | D100: C- GC | E100: =if(D100<>"",VLOOKUP(D100,Concepts!C$2:D$12,2,FALSE),"") -> Government Controls | F100: Support for development of processes and workflows including support for Robotic Process Automation, AI, machine learning
...

Sheet GRC Taxonomy
A1: Governance Risk & Compliance Taxonomy
A2: • AI assisted analysis
A3: Category | C3: Explanation
A4: 1. Fiscal and Fiduciary Governance | C4: Establishes the primary control environment, ensuring the prudent management of public resources, budget reliability, and compliance with financial legislation11. It addresses the fundamental requirement that all public expenditures must be authorized, accurate, and aligned with strategic prioritie
B5: 1.1 Policy, Macro-Fiscal Planning and Budgetary Reliability | C5: Focuses on the accuracy of revenue projections, the management of structural expenditures, the containment of off-budget fiscal decisions, and the linkage to public policy objectives
B6: 1.2 Contingent Liabilities and Fiscal Risk Analytics | C6: Addresses exposures from public procurment, infrastructure projects, State-Owned Enterprises (SOEs), Public-Private Partnerships (PPPs), calls on explicit credit guarantees, and long-term debt sustainability
B7: 1.3 Credit and Debt Program Risk | C7: Mitigates public debt, credit rating, and fiscal space risks, with unique repayment, prepayment, and market risks
B8: 1.4 Fiduciary Internal Controls and Pay Administration | C8: Manages risks associated with budget and commitment controls, spending authorizations, and segregation of duties
A9: 2. Public Integrity, Compliance, and Oversight | C9: Focuses on safeguarding the public interest, preventing systemic corruption, and ensuring that public officials adhere to high ethical standards; aligns directly with the OECD Recommendation on Public Integrity
B10: 2.1 Conflicts of Interest and Ethical Standards | C10: Monitors perceived, potential, or actual conflicts between private interests and public duties, including asset declarations, lobbying, and post-employment limitations3
B11: 2.2 Anti-Corruption, Whistleblowing, and Investigation | C11: Governs systems to prevent, detect, and sanction bribery, embezzlement, fraud, and influence trading, including secure channels for whistleblowers
B12: 2.3 External Scrutiny, Audit, and Legislative Oversight | C12: Manages the integration of findings from Supreme Audit Institutions (SAIs), the coverage of internal audit plans, and the timeliness of legislative reviews4
B13: 2.4 Reputational, Credibility, and Political Risk | C13: Mitigates credibility risk
A14: 3. Operational Resilience and Strategic Risk | C14: Governs the delivery of public programs and the capacity of governments to anticipate, prepare for, and respond to critical, large-scale crises
B15: 3.1 Program Design, Implementation, and Change Management | C15: Manages operational vulnerabilities in service delivery, including resource bottlenecks, legacy process rigidity, and organizational change management
B16: 3.2 Governance of Critical Risks and Disaster Preparedness | C16: Addresses systemic, transboundary, and cascading threats such as natural disasters, climate change disruptions, fiscal disruption, padamemics, and critical infrastructure failures
B17: 3.3 Human Capital and Talent Capacity Management | C17: Focuses on recruitment delays, key-man dependencies, critical skills gaps, and human resources planning in high-complexity environments3
A18: 4. Digital Systems and Technological Infrastructure | C18: Isolates information technology and digital assets from physical assets, reflecting the critical role of technology in modern public service delivery and the unique threats of the digital landscape
B19: 4.1 Enterprise Architecture and IT Project Governance | C19: Ensures that digital investments are aligned with organizational goals, managed through formal project frameworks, and reviewed by Architecture Review Boards (ARBs)
B20: 4.2 Cybersecurity, Information Stewardship, and Privacy | C20: Focuses on the mitigation of data breaches, ransomware attacks, insider threats, and the exfiltration of sensitive personal information
B21: 4.3 Emerging Technology and Artificial Intelligence Governance | C21: Manages the operational, compliance, and ethical risks associated with the deployment of artificial intelligence, machine learning, and automated decision-making system | E21: Data governance?
B22: 4.4 Big Data and Content Governance | C22: Manages data?
A23: 5. Environmental, Social, and Stakeholder Safeguards | C23: Eensures that government programs and investment projects avoid or mitigate adverse impacts on communities and the environment, promoting sustainable and inclusive development
B24: 5.1 Environmental Protection, Biodiversity, and Resource Efficiency | C24: Monitors project-level impacts on habitats, water resources, and pollution levels, ensuring compliance with international sustainability commitments
B25: 5.2 Social Inclusion, Human Rights, and Community Safety | C25: Manages risks related to labor conditions, gender equality, non-discrimination, community health, and the protection of vulnerable groups
B26: 5.3 Indigenous Reconciliation and Stakeholder Engagement | C26: Governs the process of meaningful, ongoing consultation, respect for traditional land rights, and the operation of responsive grievance mechanisms

Sheet New Marketecture
A1: New FreeBalance Marketecture
A3: Core Modules
A4: • core modules that can be aggregated to form comprehensive modules showing full roadmap functionality and roadmap status
A5: • modules can share functions and components (with standard some replicated components)
A6: • pricing aligns to new marketecture that is not has granular as the previous, where we can consider lower prices for lower functionality
A7: Functional Description | B7: New Marketecture | C7: Current Marketecture | D7: Development Terms | E7: Function | F7: Component | G7: S | H7: Status
A8: Policy Management | B8: =vlookup(A8,'NM Lookup'!A$15:B$33,2) -> Policy Management | C8: Not Applicable | D8: Not Applicable | E8: ='PFM Component Map'!B3 -> 1.1 Policy Management | F8: ='PFM Component Map'!C3 -> 1.1.01 Legislation Management | G8: 1 | H8: =vlookup(G8,'NM Lookup'!A$7:B$10,2) -> Low Priority
A9: Policy Management | B9: =vlookup(A9,'NM Lookup'!A$15:B$33,2) -> Policy Management | C9: Not Applicable | D9: Not Applicable | E9: ='PFM Component Map'!B4 -> 1.1 Policy Management | F9: ='PFM Component Map'!C4 -> 1.1.02 Regulation Management | G9: 1 | H9: =vlookup(G9,'NM Lookup'!A$7:B$10,2) -> Low Priority
A10: Policy Management | B10: =vlookup(A10,'NM Lookup'!A$15:B$33,2) -> Policy Management | C10: Not Applicable | D10: Not Applicable | E10: ='PFM Component Map'!B5 -> 1.1 Policy Management | F10: ='PFM Component Map'!C5 -> 1.1.03 Development Strategy & Government Goals | G10: 1 | H10: =vlookup(G10,'NM Lookup'!A$7:B$10,2) -> Low Priority
A11: Policy Management | B11: =vlookup(A11,'NM Lookup'!A$15:B$33,2) -> Policy Management | C11: Not Applicable | D11: Not Applicable | E11: ='PFM Component Map'!B6 -> 1.1 Policy Management | F11: ='PFM Component Map'!C6 -> 1.1.04 Policy Legal Framework | G11: 1 | H11: =vlookup(G11,'NM Lookup'!A$7:B$10,2) -> Low Priority
A12: Policy Management | B12: =vlookup(A12,'NM Lookup'!A$15:B$33,2) -> Policy Management | C12: Not Applicable | D12: Not Applicable | E12: ='PFM Component Map'!B7 -> 1.1 Policy Management | F12: ='PFM Component Map'!C7 -> 1.1.05 Intergovernmental Fiscal Relations | G12: 1 | H12: =vlookup(G12,'NM Lookup'!A$7:B$10,2) -> Low Priority
A13: Policy Management | B13: =vlookup(A13,'NM Lookup'!A$15:B$33,2) -> Policy Management | C13: Not Applicable | D13: Not Applicable | E13: ='PFM Component Map'!B8 -> 1.1 Policy Management | F13: ='PFM Component Map'!C8 -> 1.1.06 Fiscal Framework | G13: 1 | H13: =vlookup(G13,'NM Lookup'!A$7:B$10,2) -> Low Priority
A14: Policy Management | B14: =vlookup(A14,'NM Lookup'!A$15:B$33,2) -> Policy Management | C14: Not Applicable | D14: Not Applicable | E14: ='PFM Component Map'!B9 -> 1.1 Policy Management | F14: ='PFM Component Map'!C9 -> 1.1.07 Trend Analysis | G14: 1 | H14: =vlookup(G14,'NM Lookup'!A$7:B$10,2) -> Low Priority
A15: Policy Management | B15: =vlookup(A15,'NM Lookup'!A$15:B$33,2) -> Policy Management | C15: Not Applicable | D15: Not Applicable | E15: ='PFM Component Map'!B10 -> 1.1 Policy Management | F15: ='PFM Component Map'!C10 -> 1.1.08 Macroeconomic Forecasting | G15: 1 | H15: =vlookup(G15,'NM Lookup'!A$7:B$10,2) -> Low Priority
A16: Policy Management | B16: =vlookup(A16,'NM Lookup'!A$15:B$33,2) -> Policy Management | C16: Not Applicable | D16: Not Applicable | E16: ='PFM Component Map'!B11 -> 1.1 Policy Management | F16: ='PFM Component Map'!C11 -> 1.1.09 Policy Planning Versions | G16: 1 | H16: =vlookup(G16,'NM Lookup'!A$7:B$10,2) -> Low Priority
A17: Policy Management | B17: =vlookup(A17,'NM Lookup'!A$15:B$33,2) -> Policy Management | C17: Not Applicable | D17: Not Applicable | E17: ='PFM Component Map'!B12 -> 1.1 Policy Management | F17: ='PFM Component Map'!C12 -> 1.1.10 Policy Impact Assessment | G17: 1 | H17: =vlookup(G17,'NM Lookup'!A$7:B$10,2) -> Low Priority
A18: Policy Management | B18: =vlookup(A18,'NM Lookup'!A$15:B$33,2) -> Policy Management | C18: Not Applicable | D18: Not Applicable | E18: ='PFM Component Map'!B13 -> 1.1 Policy Management | F18: ='PFM Component Map'!C13 -> 1.1.11 Cross-Sectoral Policy Integration | G18: 1 | H18: =vlookup(G18,'NM Lookup'!A$7:B$10,2) -> Low Priority
A19: Policy Management | B19: =vlookup(A19,'NM Lookup'!A$15:B$33,2) -> Policy Management | C19: Not Applicable | D19: Not Applicable | E19: ='PFM Component Map'!B14 -> 1.1 Policy Management | F19: ='PFM Component Map'!C14 -> 1.1.12 International Commitments & Agreements | G19: 1 | H19: =vlookup(G19,'NM Lookup'!A$7:B$10,2) -> Low Priority
... A48: Budget Preperation | B48: =vlookup(A48,'NM Lookup'!A$15:B$33,2) -> Government Budget Formulation | C48: Performance Budgeting | D48: Budget Planning | E48: ='PFM Component Map'!B43 -> 1.3 Public Accounts Management | F48: ='PFM Component Map'!C43 -> 1.3.01 Accounting Regulatory Framework | G48: 4 | H48: =vlookup(G48,'NM Lookup'!A$7:B$10,2) -> Available
A49: Budget Preperation | B49: =vlookup(A49,'NM Lookup'!A$15:B$33,2) -> Government Budget Formulation | C49: Performance Budgeting | D49: Budget Planning | E49: =E574 -> 1.3 Public Accounts Management | F49: =F574 -> 1.3.01 Accounting Regulatory Framework | G49: =G574 -> 4 | H49: =H574 -> Available
A50: Budget Preperation | B50: =vlookup(A50,'NM Lookup'!A$15:B$33,2) -> Government Budget Formulation | C50: Performance Budgeting | D50: Budget Planning | E50: =E575 -> 1.3 Public Accounts Management | F50: =F575 -> 1.3.02 Accounting Policies | G50: =G575 -> 4 | H50: =H575 -> Available
A51: Budget Preperation | B51: =vlookup(A51,'NM Lookup'!A$15:B$33,2) -> Government Budget Formulation | C51: Performance Budgeting | D51: Budget Planning | E51: =E576 -> 1.3 Public Accounts Management | F51: =F576 -> 1.3.03 Accounting Codes in Chart of Accounts | G51: =G576 -> 4 | H51: =H576 -> Available
A52: Budget Preperation | B52: =vlookup(A52,'NM Lookup'!A$15:B$33,2) -> Government Budget Formulation | C52: Performance Budgeting | D52: Budget Planning | E52: =E577 -> 1.3 Public Accounts Management | F52: =F577 -> 1.3.04 Budget Classifications in Chart of Accounts | G52: =G577 -> 4 | H52: =H577 -> Available
A53: Budget Preperation | B53: =vlookup(A53,'NM Lookup'!A$15:B$33,2) -> Government Budget Formulation | C53: Performance Budgeting | D53: Budget Planning | E53: =E578 -> 1.3 Public Accounts Management | F53: =F578 -> 1.3.05 Program Classifications in Chart of Accounts | G53: =G578 -> 4 | H53: =H578 -> Available
A54: Budget Preperation | B54: =vlookup(A54,'NM Lookup'!A$15:B$33,2) -> Government Budget Formulation | C54: Performance Budgeting | D54: Budget Planning | E54: =E579 -> 1.3 Public Accounts Management | F54: =F579 -> 1.3.06 National Standards in Chart of Accounts | G54: =G579 -> 4 | H54: =H579 -> Available
A55: Budget Preperation | B55: =vlookup(A55,'NM Lookup'!A$15:B$33,2) -> Government Budget Formulation | C55: Performance Budgeting | D55: Budget Planning | E55: =E580 -> 1.3 Public Accounts Management | F55: =F580 -> 1.3.07 International Standards in Chart of Accounts | G55: =G580 -> 4 | H55: =H580 -> Available
A56: Budget Preperation | B56: =vlookup(A56,'NM Lookup'!A$15:B$33,2) -> Government Budget Formulation | C56: Performance Budgeting | D56: Budget Planning | E56: =E581 -> 1.3 Public Accounts Management | F56: =F581 -> 1.3.08 Sustainable Development Goals in Chart of Accounts | G56: =G581 -> 4 | H56: =H581 -> Available
A57: Budget Preperation | B57: =vlookup(A57,'NM Lookup'!A$15:B$33,2) -> Government Budget Formulation | C57: Performance Budgeting | D57: Budget Planning | E57: =E582 -> 1.3 Public Accounts Management | F57: =F582 -> 1.3.09 Gender, Wellbeing and Inclusion in Chart of Accounts | G57: =G582 -> 4 | H57: =H582 -> Available
A58: Budget Preperation | B58: =vlookup(A58,'NM Lookup'!A$15:B$33,2) -> Government Budget Formulation | C58: Performance Budgeting | D58: Budget Planning | E58: =E583 -> 1.3 Public Accounts Management | F58: =F583 -> 1.3.10 Reporting Objects | G58: =G583 -> 4 | H58: =H583 -> Available
A59: Budget Preperation | B59: =vlookup(A59,'NM Lookup'!A$15:B$33,2) -> Government Budget Formulation | C59: Performance Budgeting | D59: Budget Planning | E59: =E584 -> 1.3 Public Accounts Management | F59: =F584 -> 1.3.11 PEFA Assessments | G59: =G584 -> 4 | H59: =H584 -> Available
A60: Budget Preperation | B60: =vlookup(A60,'NM Lookup'!A$15:B$33,2) -> Government Budget Formulation | C60: Performance Budgeting | D60: Budget Planning | E60: =E585 -> 1.3 Public Accounts Management | F60: =F585 -> 1.3.A1 Chart of Accounts Additions | G60: =G585 -> 4 | H60: =H585 -> Available
A61: Budget Preperation | B61: =vlookup(A61,'NM Lookup'!A$15:B$33,2) -> Government Budget Formulation | C61: Performance Budgeting | D61: Budget Planning | E61: ='PFM Component Map'!B43 -> 1.3 Public Accounts Management | F61: ='PFM Component Map'!C56 -> 1.3.T1 Government Classification Transparency | G61: 1 | H61: =vlookup(G61,'NM Lookup'!A$7:B$10,2) -> Low Priority
A62: Performance and Transparency | B62: Fiscal Performance and Transparency | C62: Performance Management & Portals | D62: ? | E62: ='PFM Component Map'!B57 -> 1.4 Performance Structures & Implementation | F62: ='PFM Component Map'!C57 -> 1.4.01 Output Performance Indicators / Targets | G62: 4 | H62: =vlookup(G62,'NM Lookup'!A$7:B$10,2) -> Available
A63: Performance and Transparency | B63: Fiscal Performance and Transparency | C63: Performance Management & Portals | D63: ? | E63: ='PFM Component Map'!B58 -> 1.4 Performance Structures & Implementation | F63: ='PFM Component Map'!C58 -> 1.4.02 Chart of Goals integrated with Chart of Accounts | G63: 4 | H63: =vlookup(G63,'NM Lookup'!A$7:B$10,2) -> Available
A64: Performance and Transparency | B64: Fiscal Performance and Transparency | C64: Performance Management & Portals | D64: ? | E64: ='PFM Component Map'!B59 -> 1.4 Performance Structures & Implementation | F64: ='PFM Component Map'!C59 -> 1.4.03 Public Finance Analytics | G64: 4 | H64: =vlookup(G64,'NM Lookup'!A$7:B$10,2) -> Available
A65: Performance and Transparency | B65: Fiscal Performance and Transparency | C65: Performance Management & Portals | D65: ? | E65: ='PFM Component Map'!B60 -> 1.4 Performance Structures & Implementation | F65: ='PFM Component Map'!C60 -> 1.4.04 Public Finance Visualization | G65: 4 | H65: =vlookup(G65,'NM Lookup'!A$7:B$10,2) -> Available
A66: Performance and Transparency | B66: Fiscal Performance and Transparency | C66: Performance Management & Portals | D66: ? | E66: ='PFM Component Map'!B61 -> 1.4 Performance Structures & Implementation | F66: ='PFM Component Map'!C61 -> 1.4.05 Performance Presentation | G66: 3 | H66: =vlookup(G66,'NM Lookup'!A$7:B$10,2) -> High Priority
A67: Performance and Transparency | B67: Fiscal Performance and Transparency | C67: Performance Management & Portals | D67: ? | E67: ='PFM Component Map'!B62 -> 1.4 Performance Structures & Implementation | F67: ='PFM Component Map'!C62 -> 1.4.06 Public Finance Storytelling | G67: 1 | H67: =vlookup(G67,'NM Lookup'!A$7:B$10,2) -> Low Priority
A68: Performance and Transparency | B68: Fiscal Performance and Transparency | C68: Performance Management & Portals | D68: ? | E68: ='PFM Component Map'!B63 -> 1.4 Performance Structures & Implementation | F68: ='PFM Component Map'!C63 -> 1.4.07 Spending Reviews | G68: 1 | H68: =vlookup(G68,'NM Lookup'!A$7:B$10,2) -> Low Priority
A69: Performance and Transparency | B69: Fiscal Performance and Transparency | C69: Performance Management & Portals | D69: ? | E69: ='PFM Component Map'!B64 -> 1.4 Performance Structures & Implementation | F69: ='PFM Component Map'!C64 -> 1.4.08 Peer Benchmarking & Global Comparisons | G69: 1 | H69: =vlookup(G69,'NM Lookup'!A$7:B$10,2) -> Low Priority
A70: Performance and Transparency | B70: Fiscal Performance and Transparency | C70: Performance Management & Portals | D70: ? | E70: ='PFM Component Map'!B65 -> 1.4 Performance Structures & Implementation | F70: ='PFM Component Map'!C65 -> 1.4.08 Monitoring & Evaluation (M&E) Frameworks | G70: 1 | H70: =vlookup(G70,'NM Lookup'!A$7:B$10,2) -> Low Priority
A71: Performance and Transparency | B71: Fiscal Performance and Transparency | C71: Performance Management & Portals | D71: ? | E71: ='PFM Component Map'!B66 -> 1.4 Performance Structures & Implementation | F71: ='PFM Component Map'!C66 -> 1.4.09 PEFA Assessments | G71: 1 | H71: =vlookup(G71,'NM Lookup'!A$7:B$10,2) -> Low Priority
A72: Performance and Transparency | B72: Fiscal Performance and Transparency | C72: Performance Management & Portals | D72: ? | E72: ='PFM Component Map'!B67 -> 1.4 Performance Structures & Implementation | F72: ='PFM Component Map'!C67 -> 1.4.A1 Chart of Goals Additions | G72: 4 | H72: =vlookup(G72,'NM Lookup'!A$7:B$10,2) -> Available
A73: Performance and Transparency | B73: Fiscal Performance and Transparency | C73: Performance Management & Portals | D73: ? | E73: ='PFM Component Map'!B68 -> 1.4 Performance Structures & Implementation | F73: ='PFM Component Map'!C68 -> 1.4.A2 Multiple-Year Chart of Goals | G73: 4 | H73: =vlookup(G73,'NM Lookup'!A$7:B$10,2) -> Available
A74: Performance and Transparency | B74: Fiscal Performance and Transparency | C74: Performance Management & Portals | D74: ? | E74: ='PFM Component Map'!B69 -> 1.4 Performance Structures & Implementation | F74: ='PFM Component Map'!C69 -> 1.4.T1 E-Performance Transparency | G74: 1 | H74: =vlookup(G74,'NM Lookup'!A$7:B$10,2) -> Low Priority
A75: Performance and Transparency | B75: Fiscal Performance and Transparency | C75: Duplicated in T items by product | E75: =E74 -> 1.4 Performance Structures & Implementation | F75: Ts | G75: 3 | H75: =vlookup(G75,'NM Lookup'!A$7:B$10,2) -> High Priority
A76: Core Financials | B76: Core Financial Execution and Reporting | C76: Core Financials | D76: ? | E76: ='PFM Component Map'!B70 -> 2.1 Budget and Appropriation Control | F76: ='PFM Component Map'!C70 -> 2.1.01 Budget Controls | G76: 4 | H76: =vlookup(G76,'NM Lookup'!A$7:B$10,2) -> Available
A77: Core Financials | B77: Core Financial Execution and Reporting | C77: Core Financials | D77: ? | E77: ='PFM Component Map'!B71 -> 2.1 Budget and Appropriation Control | F77: ='PFM Component Map'!C71 -> 2.1.02 Financial Regulations | G77: 4 | H77: =vlookup(G77,'NM Lookup'!A$7:B$10,2) -> Available
A78: Core Financials | B78: Core Financial Execution and Reporting | C78: Core Financials | D78: ? | E78: ='PFM Component Map'!B72 -> 2.1 Budget and Appropriation Control | F78: ='PFM Component Map'!C72 -> 2.1.03 Appropriations & Warrants | G78: 4 | H78: =vlookup(G78,'NM Lookup'!A$7:B$10,2) -> Available
A79: Core Financials | B79: Core Financial Execution and Reporting | C79: Core Financials | D79: ? | E79: ='PFM Component Map'!B73 -> 2.1 Budget and Appropriation Control | F79: ='PFM Component Map'!C73 -> 2.1.04 Fiscal Rules | G79: 4 | H79: =vlookup(G79,'NM Lookup'!A$7:B$10,2) -> Available
A80: Core Financials | B80: Core Financial Execution and Reporting | C80: Core Financials | D80: ? | E80: ='PFM Component Map'!B74 -> 2.1 Budget and Appropriation Control | F80: ='PFM Component Map'!C74 -> 2.1.05 Segregation of Duties | G80: 4 | H80: =vlookup(G80,'NM Lookup'!A$7:B$10,2) -> Available
A81: Core Financials | B81: Core Financial Execution and Reporting | C81: Core Financials | D81: ? | E81: ='PFM Component Map'!B75 -> 2.1 Budget and Appropriation Control | F81: ='PFM Component Map'!C75 -> 2.1.06 Budget Requests | G81: 4 | H81: =vlookup(G81,'NM Lookup'!A$7:B$10,2) -> Available
A82: Core Financials | B82: Core Financial Execution and Reporting | C82: Core Financials | D82: ? | E82: ='PFM Component Map'!B76 -> 2.1 Budget and Appropriation Control | F82: ='PFM Component Map'!C76 -> 2.1.A1 Budget and Appropriation Approvals | G82: 4 | H82: =vlookup(G82,'NM Lookup'!A$7:B$10,2) -> Available
A83: Core Financials | B83: Core Financial Execution and Reporting | C83: Core Financials | D83: ? | E83: ='PFM Component Map'!B77 -> 2.1 Budget and Appropriation Control | F83: ='PFM Component Map'!C77 -> 2.1.T1 Initial Budget Transparency | G83: 4 | H83: =vlookup(G83,'NM Lookup'!A$7:B$10,2) -> Available
A84: Core Financials | B84: Core Financial Execution and Reporting | C84: Core Financials | D84: ? | E84: ='PFM Component Map'!B78 -> 2.2 Commitment Management | F84: ='PFM Component Map'!C78 -> 2.2.01 Commitments | G84: 4 | H84: =vlookup(G84,'NM Lookup'!A$7:B$10,2) -> Available
A85: Core Financials | B85: Core Financial Execution and Reporting | C85: Core Financials | D85: ? | E85: ='PFM Component Map'!B79 -> 2.2 Commitment Management | F85: ='PFM Component Map'!C79 -> 2.2.02 Obligations | G85: 4 | H85: =vlookup(G85,'NM Lookup'!A$7:B$10,2) -> Available
A86: Core Financials | B86: Core Financial Execution and Reporting | C86: Core Financials | D86: ? | E86: ='PFM Component Map'!B80 -> 2.2 Commitment Management | F86: ='PFM Component Map'!C80 -> 2.2.03 Multiple-Year Commitments | G86: 4 | H86: =vlookup(G86,'NM Lookup'!A$7:B$10,2) -> Available
A87: Core Financials | B87: Core Financial Execution and Reporting | C87: Core Financials | D87: ? | E87: ='PFM Component Map'!B81 -> 2.2 Commitment Management | F87: ='PFM Component Map'!C81 -> 2.2.04 Multiple-Year Obligations | G87: 4 | H87: =vlookup(G87,'NM Lookup'!A$7:B$10,2) -> Available
... A103: Core Financials | B103: Core Financial Execution and Reporting | C103: Core Financials | D103: ? | E103: ='PFM Component Map'!B97 -> 2.3 Budget Execution | F103: ='PFM Component Map'!C97 -> 2.3.T1 Budget Execution Transparency | G103: 4 | H103: =vlookup(G103,'NM Lookup'!A$7:B$10,2) -> Available
A104: Core Financials | B104: Core Financial Execution and Reporting | C104: Core Financials | D104: ? | E104: ='PFM Component Map'!B120 -> 3.1 Treasury Accounting | F104: ='PFM Component Map'!C120 -> 3.1.01 Journals | G104: 4 | H104: =vlookup(G104,'NM Lookup'!A$7:B$10,2) -> Available
A105: Core Financials | B105: Core Financial Execution and Reporting | C105: Core Financials | D105: ? | E105: ='PFM Component Map'!B121 -> 3.1 Treasury Accounting | F105: ='PFM Component Map'!C121 -> 3.1.02 General Ledger | G105: 4 | H105: =vlookup(G105,'NM Lookup'!A$7:B$10,2) -> Available
A106: Core Financials | B106: Core Financial Execution and Reporting | C106: Core Financials | D106: ? | E106: ='PFM Component Map'!B122 -> 3.1 Treasury Accounting | F106: ='PFM Component Map'!C122 -> 3.1.03 Accounts Receivable | G106: 4 | H106: =vlookup(G106,'NM Lookup'!A$7:B$10,2) -> Available
A107: Core Financials | B107: Core Financial Execution and Reporting | C107: Core Financials | D107: ? | E107: ='PFM Component Map'!B123 -> 3.1 Treasury Accounting | F107: ='PFM Component Map'!C123 -> 3.1.04 Accounts Payables | G107: 4 | H107: =vlookup(G107,'NM Lookup'!A$7:B$10,2) -> Available
A108: Core Financials | B108: Core Financial Execution and Reporting | C108: Core Financials | D108: ? | E108: ='PFM Component Map'!B124 -> 3.1 Treasury Accounting | F108: ='PFM Component Map'!C124 -> 3.1.05 Sub-Ledgers | G108: 4 | H108: =vlookup(G108,'NM Lookup'!A$7:B$10,2) -> Available
A109: Core Financials | B109: Core Financial Execution and Reporting | C109: Core Financials | D109: ? | E109: ='PFM Component Map'!B125 -> 3.1 Treasury Accounting | F109: ='PFM Component Map'!C125 -> 3.1.06 Financial Consolidation | G109: 4 | H109: =vlookup(G109,'NM Lookup'!A$7:B$10,2) -> Available
A110: Core Financials | B110: Core Financial Execution and Reporting | C110: Core Financials | D110: ? | E110: ='PFM Component Map'!B126 -> 3.1 Treasury Accounting | F110: ='PFM Component Map'!C126 -> 3.1.07 Period-Ending Procedures | G110: 4 | H110: =vlookup(G110,'NM Lookup'!A$7:B$10,2) -> Available
A111: Core Financials | B111: Core Financial Execution and Reporting | C111: Core Financials | D111: ? | E111: ='PFM Component Map'!B127 -> 3.1 Treasury Accounting | F111: ='PFM Component Map'!C127 -> 3.1.08 Year-End Procedures | G111: 4 | H111: =vlookup(G111,'NM Lookup'!A$7:B$10,2) -> Available
A112: Core Financials | B112: Core Financial Execution and Reporting | C112: Core Financials | D112: ? | E112: ='PFM Component Map'!B128 -> 3.1 Treasury Accounting | F112: ='PFM Component Map'!C128 -> 3.1.09 Financial Notes | G112: 4 | H112: =vlookup(G112,'NM Lookup'!A$7:B$10,2) -> Available
A113: Core Financials | B113: Core Financial Execution and Reporting | C113: Core Financials | D113: ? | E113: ='PFM Component Map'!B129 -> 3.1 Treasury Accounting | F113: ='PFM Component Map'!C129 -> 3.1.10 Accrual & Cash Basis Accounting Support | G113: 4 | H113: =vlookup(G113,'NM Lookup'!A$7:B$10,2) -> Available
A114: Core Financials | B114: Core Financial Execution and Reporting | C114: Core Financials | D114: ? | E114: ='PFM Component Map'!B130 -> 3.1 Treasury Accounting | F114: ='PFM Component Map'!C130 -> 3.1.11 Contingent Liabilities | G114: 4 | H114: =vlookup(G114,'NM Lookup'!A$7:B$10,2) -> Available
A115: Core Financials | B115: Core Financial Execution and Reporting | C115: Core Financials | D115: ? | E115: ='PFM Component Map'!B131 -> 3.1 Treasury Accounting | F115: ='PFM Component Map'!C131 -> 3.1.12 Accruals Adjustment | G115: 4 | H115: =vlookup(G115,'NM Lookup'!A$7:B$10,2) -> Available
... A124: Core Financials | B124: Core Financial Execution and Reporting | C124: Core Financials | D124: ? | E124: ='PFM Component Map'!B140 -> 3.1 Treasury Accounting | F124: ='PFM Component Map'!C140 -> 3.1.T5 Vendor & Civil Society Feedback | G124: 4 | H124: =vlookup(G124,'NM Lookup'!A$7:B$10,2) -> Available
A125: Core Financials | B125: Core Financial Execution and Reporting | C125: Core Financials | E125: ='PFM Component Map'!B141 -> 3.1 Treasury Accounting | F125: ='PFM Component Map'!C141 -> 3.1.T6 Off-Budget Management | G125: 1 | H125: =vlookup(G125,'NM Lookup'!A$7:B$10,2) -> Low Priority
A126: Core Financials | B126: Core Financial Execution and Reporting | C126: Core Financials | D126: ? | E126: ='PFM Component Map'!B142 -> 3.2 Cost Accounting | F126: ='PFM Component Map'!C142 -> 3.2.01 Project Accounting | G126: 4 | H126: =vlookup(G126,'NM Lookup'!A$7:B$10,2) -> Available
A127: Core Financials | B127: Core Financial Execution and Reporting | C127: Core Financials | D127: ? | E127: ='PFM Component Map'!B143 -> 3.2 Cost Accounting | F127: ='PFM Component Map'!C143 -> 3.2.02 Project Scheduling | G127: 3 | H127: =vlookup(G127,'NM Lookup'!A$7:B$10,2) -> High Priority
A128: Core Financials | B128: Core Financial Execution and Reporting | C128: Core Financials | D128: ? | E128: ='PFM Component Map'!B144 -> 3.2 Cost Accounting | F128: ='PFM Component Map'!C144 -> 3.2.03 Cost Accounting & Activity Based Costing | G128: 4 | H128: =vlookup(G128,'NM Lookup'!A$7:B$10,2) -> Available
A129: Core Financials | B129: Core Financial Execution and Reporting | C129: Core Financials | D129: ? | E129: ='PFM Component Map'!B145 -> 3.2 Cost Accounting | F129: ='PFM Component Map'!C145 -> 3.2.04 Job Costing | G129: 1 | H129: =vlookup(G129,'NM Lookup'!A$7:B$10,2) -> Low Priority
A130: Core Financials | B130: Core Financial Execution and Reporting | C130: Core Financials | D130: ? | E130: ='PFM Component Map'!B146 -> 3.2 Cost Accounting | F130: ='PFM Component Map'!C146 -> 3.2.05 Public Works | G130: 1 | H130: =vlookup(G130,'NM Lookup'!A$7:B$10,2) -> Low Priority
A131: Core Financials | B131: Core Financial Execution and Reporting | C131: Core Financials | D131: ? | E131: ='PFM Component Map'!B147 -> 3.2 Cost Accounting | F131: ='PFM Component Map'!C147 -> 3.2.06 Lifecycle Costing | G131: 1 | H131: =vlookup(G131,'NM Lookup'!A$7:B$10,2) -> Low Priority
A132: Core Financials | B132: Core Financial Execution and Reporting | C132: Core Financials | D132: ? | E132: ='PFM Component Map'!B148 -> 3.2 Cost Accounting | F132: ='PFM Component Map'!C148 -> 3.2.07 Overhead Allocation | G132: 1 | H132: =vlookup(G132,'NM Lookup'!A$7:B$10,2) -> Low Priority
A133: Core Financials | B133: Core Financial Execution and Reporting | C133: Core Financials | D133: ? | E133: ='PFM Component Map'!B149 -> 3.2 Cost Accounting | F133: ='PFM Component Map'!C149 -> 3.2.08 Performance & Output Costing | G133: 1 | H133: =vlookup(G133,'NM Lookup'!A$7:B$10,2) -> Low Priority
A134: Core Financials | B134: Core Financial Execution and Reporting | C134: Core Financials | D134: ? | E134: ='PFM Component Map'!B150 -> 3.2 Cost Accounting | F134: ='PFM Component Map'!C150 -> 3.2.09 Environmental & Climate Costing | G134: 1 | H134: =vlookup(G134,'NM Lookup'!A$7:B$10,2) -> Low Priority
A135: Core Financials | B135: Core Financial Execution and Reporting | C135: Core Financials | D135: ? | E135: ='PFM Component Map'!B151 -> 3.2 Cost Accounting | F135: ='PFM Component Map'!C151 -> 3.2.10 Unit Costing for Public Services | G135: 1 | H135: =vlookup(G135,'NM Lookup'!A$7:B$10,2) -> Low Priority
A136: Core Financials | B136: Core Financial Execution and Reporting | C136: Core Financials | D136: ? | E136: ='PFM Component Map'!B152 -> 3.2 Cost Accounting | F136: ='PFM Component Map'!C152 -> 3.2.11 Shared Services Costing | G136: 1 | H136: =vlookup(G136,'NM Lookup'!A$7:B$10,2) -> Low Priority
A137: Core Financials | B137: Core Financial Execution and Reporting | C137: Core Financials | D137: ? | E137: ='PFM Component Map'!B153 -> 3.2 Cost Accounting | F137: ='PFM Component Map'!C153 -> 3.2.A1 Project Approvals | G137: 4 | H137: =vlookup(G137,'NM Lookup'!A$7:B$10,2) -> Available
... A139: Core Financials | B139: Core Financial Execution and Reporting | C139: Core Financials | D139: ? | E139: ='PFM Component Map'!B155 -> 3.2 Cost Accounting | F139: ='PFM Component Map'!C155 -> 3.2.T2 Costing Transparency | G139: 1 | H139: =vlookup(G139,'NM Lookup'!A$7:B$10,2) -> Low Priority
A140: Audit | B140: Risk and Performance Audit | C140: Audit Management | D140: ? | E140: ='PFM Component Map'!B98 -> 2.4 Compliance and Governance | F140: ='PFM Component Map'!C98 -> 2.4.01 Organizational Structures | G140: 1 | H140: =vlookup(G140,'NM Lookup'!A$7:B$10,2) -> Low Priority
A141: Audit | B141: Risk and Performance Audit | C141: Audit Management | D141: ? | E141: ='PFM Component Map'!B99 -> 2.4 Compliance and Governance | F141: ='PFM Component Map'!C99 -> 2.4.02 Regulatory Compliance | G141: 1 | H141: =vlookup(G141,'NM Lookup'!A$7:B$10,2) -> Low Priority
A142: Audit | B142: Risk and Performance Audit | C142: Audit Management | D142: ? | E142: ='PFM Component Map'!B100 -> 2.4 Compliance and Governance | F142: ='PFM Component Map'!C100 -> 2.4.03 Process Development | G142: 1 | H142: =vlookup(G142,'NM Lookup'!A$7:B$10,2) -> Low Priority
A143: Audit | B143: Risk and Performance Audit | C143: Audit Management | D143: ? | E143: ='PFM Component Map'!B101 -> 2.4 Compliance and Governance | F143: ='PFM Component Map'!C101 -> 2.4.04 Process Management | G143: 1 | H143: =vlookup(G143,'NM Lookup'!A$7:B$10,2) -> Low Priority
A144: Audit | B144: Risk and Performance Audit | C144: Audit Management | D144: ? | E144: ='PFM Component Map'!B102 -> 2.4 Compliance and Governance | F144: ='PFM Component Map'!C102 -> 2.4.05 Document and Records Control | G144: 1 | H144: =vlookup(G144,'NM Lookup'!A$7:B$10,2) -> Low Priority
A145: Audit | B145: Risk and Performance Audit | C145: Audit Management | D145: ? | E145: ='PFM Component Map'!B103 -> 2.4 Compliance and Governance | F145: ='PFM Component Map'!C103 -> 2.4.06 Document and Records Management | G145: 1 | H145: =vlookup(G145,'NM Lookup'!A$7:B$10,2) -> Low Priority
A146: Audit | B146: Risk and Performance Audit | C146: Audit Management | D146: ? | E146: ='PFM Component Map'!B104 -> 2.4 Compliance and Governance | F146: ='PFM Component Map'!C104 -> 2.4.07 Audit Case Management | G146: 4 | H146: =vlookup(G146,'NM Lookup'!A$7:B$10,2) -> Available
A147: Audit | B147: Risk and Performance Audit | C147: Audit Management | D147: ? | E147: ='PFM Component Map'!B105 -> 2.4 Compliance and Governance | F147: ='PFM Component Map'!C105 -> 2.4.08 Audit Data Analysis | G147: 1 | H147: =vlookup(G147,'NM Lookup'!A$7:B$10,2) -> Low Priority
A148: Audit | B148: Risk and Performance Audit | C148: Audit Management | D148: ? | E148: ='PFM Component Map'!B106 -> 2.4 Compliance and Governance | F148: ='PFM Component Map'!C106 -> 2.4.09 Additional Oversight Management | G148: 1 | H148: =vlookup(G148,'NM Lookup'!A$7:B$10,2) -> Low Priority
A149: Audit | B149: Risk and Performance Audit | C149: Parliamentary Oversight | D149: ? | E149: ='PFM Component Map'!B107 -> 2.4 Compliance and Governance | F149: ='PFM Component Map'!C107 -> 2.4.10 Legislative & Judicial Financial Oversight | G149: 4 | H149: =vlookup(G149,'NM Lookup'!A$7:B$10,2) -> Available
A150: Audit | B150: Risk and Performance Audit | C150: Audit Management | D150: ? | E150: ='PFM Component Map'!B108 -> 2.4 Compliance and Governance | F150: ='PFM Component Map'!C108 -> 2.4.11 Access to Information Legislation | G150: 1 | H150: =vlookup(G150,'NM Lookup'!A$7:B$10,2) -> Low Priority
A151: Audit | B151: Risk and Performance Audit | C151: Audit Management | D151: ? | E151: ='PFM Component Map'!B109 -> 2.4 Compliance and Governance | F151: ='PFM Component Map'!C109 -> 2.4.12 Compliance with International Financial Institutions (IFIs) | G151: 1 | H151: =vlookup(G151,'NM Lookup'!A$7:B$10,2) -> Low Priority
... A160: Audit | B160: Risk and Performance Audit | C160: Audit Management | D160: ? | E160: ='PFM Component Map'!B118 -> 2.4 Compliance and Governance | F160: ='PFM Component Map'!C118 -> 2.4.T4 Access to Information | G160: 1 | H160: =vlookup(G160,'NM Lookup'!A$7:B$10,2) -> Low Priority
A161: Audit | B161: Risk and Performance Audit | C161: Audit Management | E161: 2.4 Compliance and Governance | F161: 2.4.T5 Corruption Reporting | G161: 1 | H161: =vlookup(G161,'NM Lookup'!A$7:B$10,2) -> Low Priority
...

Sheet Current Marketecture
A1: Current FreeBalance Marketecture
A3: Purpose: Map current FreeBalance Marketecture to proposed New Marketecture (does not include interfaces)
A4: • Available: whether module is available
A5: • Built-In: whether a built-in Platform functionality, not priced
A6: • Invent: invented product, really the same as a previous
A7: • 3rd: available as a 3rd party product
A8: • In New: whether part of the new marketecture
A9: • Subset: represents a subset of functionliatyin the new marketecture
A11: Marketecture
C12: Product Status
A13: Pillar | B13: Product | C13: Available | D13: Built-in | E13: Invent | F13: 3rd | G13: In New | H13: Subset
A14: GPM | B14: (GPAC) Anti-Corruption Reporting | C14: FALSE | D14: FALSE | E14: FALSE | F14: FALSE | G14: FALSE | H14: FALSE
A15: GPM | B15: (GPAM) Audit Management | C15: TRUE | D15: FALSE | E15: FALSE | F15: FALSE | G15: FALSE | H15: FALSE
A16: GPM | B16: (GPBB) Budget Book Builder | C16: TRUE | D16: FALSE | E16: FALSE | F16: FALSE | G16: FALSE | H16: TRUE
A17: GPM | B17: (GPBD) Big Data Management | C17: FALSE | D17: FALSE | E17: FALSE | F17: FALSE | G17: FALSE | H17: FALSE
A18: GPM | B18: (GPCA) Computer-Assisted Audit | C18: FALSE | D18: FALSE | E18: FALSE | F18: TRUE | G18: FALSE | H18: FALSE
A19: GPM | B19: (GPCE) President/Prime Minister Dashboard | C19: TRUE | D19: FALSE | E19: FALSE | F19: FALSE | G19: FALSE | H19: FALSE
A20: GPM | B20: (GPCM) Correspondence Management | C20: FALSE | D20: FALSE | E20: FALSE | F20: TRUE | G20: FALSE | H20: FALSE
A21: GPM | B21: (GPCO) Citizens Outreach | C21: FALSE | D21: FALSE | E21: FALSE | F21: FALSE | G21: FALSE | H21: FALSE
A22: GPM | B22: (GPCR) Customized Reporting | C22: TRUE | D22: FALSE | E22: FALSE | F22: TRUE | G22: FALSE | H22: FALSE
A23: GPM | B23: (GPCT) Court Case Tracking | C23: TRUE | D23: FALSE | E23: FALSE | F23: FALSE | G23: FALSE | H23: FALSE
A24: GPM | B24: (GPDM) FreeBalance Datamart | C24: TRUE | D24: FALSE | E24: FALSE | F24: FALSE | G24: FALSE | H24: FALSE
A25: GPM | B25: (GPMA) Management Alerts | C25: TRUE | D25: TRUE | E25: FALSE | F25: FALSE | G25: FALSE | H25: FALSE
... A71: GTM | B71: (GTTM) Treasury Management | C71: TRUE | D71: FALSE | E71: FALSE | F71: FALSE | G71: FALSE | H71: FALSE
A72: GTM | B72: (GTBR) Bank Reconciliation | C72: TRUE | D72: TRUE | E72: FALSE | F72: FALSE | G72: FALSE | H72: FALSE | J72: current price list
A73: GTM | B73: (GTBT) Bank Account Transfers[V6] | C73: TRUE | D73: FALSE | E73: FALSE | F73: FALSE | G73: FALSE | H73: FALSE
A74: GTM | B74: (GTCM) Cash Management | C74: TRUE | D74: TRUE | E74: FALSE | F74: FALSE | G74: FALSE | H74: FALSE
A75: GTM | B75: (GTDM) Debt Management | C75: TRUE | D75: FALSE | E75: FALSE | F75: FALSE | G75: FALSE | H75: FALSE
A76: GTM | B76: (GTDP) Debt Planning and Forecasting | C76: FALSE | D76: FALSE | E76: FALSE | F76: FALSE | G76: FALSE | H76: FALSE | J76: triangulate with PFMCM
A77: GTM | B77: (GTIM) Investment Management | C77: TRUE | D77: FALSE | E77: FALSE | F77: FALSE | G77: FALSE | H77: FALSE
A78: GTM | B78: (GTIT) Government Departmental Transfers | C78: TRUE | D78: TRUE | E78: FALSE | F78: FALSE | G78: FALSE | H78: FALSE
A79: GTM | B79: (GTLM) Liquidity Management | C79: FALSE | D79: FALSE | E79: FALSE | F79: FALSE | G79: FALSE | H79: FALSE
A80: GTM | B80: (GTNB) National Bank Software | C80: FALSE | D80: FALSE | E80: FALSE | F80: FALSE | G80: FALSE | H80: FALSE
A81: GTM | B81: (GTPM) Payment Management | C81: TRUE | D81: FALSE | E81: FALSE | F81: FALSE | G81: FALSE | H81: FALSE
A82: GTM | B82: (GTRM) Risk Management | C82: FALSE | D82: FALSE | E82: FALSE | F82: FALSE | G82: FALSE | H82: FALSE
A83: PEM | B83: (PECM) Contract Management | C83: TRUE | D83: FALSE | E83: FALSE | F83: FALSE | G83: FALSE | H83: FALSE
A84: PEM | B84: (PEEA) E-Auctions | C84: FALSE | D84: FALSE | E84: FALSE | F84: FALSE | G84: FALSE | H84: FALSE
A85: PEM | B85: (PEEA) E-Bidding | C85: FALSE | D85: FALSE | E85: FALSE | F85: FALSE | G85: FALSE | H85: FALSE
A86: PEM | B86: (PECT) Catalogue Management | C86: TRUE | D86: TRUE | E86: FALSE | F86: FALSE | G86: FALSE | H86: FALSE
A87: PEM | B87: (PEEP) e-Procurement Portal | C87: TRUE | D87: FALSE | E87: FALSE | F87: FALSE | G87: FALSE | H87: FALSE
A88: PEM | B88: (PEER) Public Investment Results Portal | C88: FALSE | D88: FALSE | E88: FALSE | F88: FALSE | G88: FALSE | H88: FALSE
... A144: CSM | B144: (CSSB) Salary Budget Planning | C144: TRUE | D144: FALSE | E144: FALSE | F144: FALSE | G144: FALSE | H144: FALSE
A145: Totals | B145: =COUNTA(B12:B144) -> 132 | C145: =countif(C12:C144,TRUE) -> 66 | D145: =countif(D12:D144,TRUE) -> 12 | E145: =countif(E12:E144,TRUE) -> 0 | F145: =countif(F12:F144,TRUE) -> 5 | G145: =countif(G12:G144,TRUE) -> 0 | H145: =countif(H12:H144,TRUE) -> 12

Sheet NM Lookup
A1: New FreeBalance Marketecture
A2: Lookup
A4: Status Lookup
A5: • colour-code product status for easy reference
A6: S | B6: Status
A7: 1 | B7: Low Priority
A8: 2 | B8: Medium Priority
A9: 3 | B9: High Priority
A10: 4 | B10: Available
A12: Product Lookup
A13: • align product functional description to markecture name
A14: Description | B14: Marketecture Name | C14: To Market
A15: Assets and Inventory | B15: Asset and Inventory Lifecycle | C15: TRUE
A16: Audit | B16: Risk and Performance Audit | C16: TRUE
A17: Budget Preparation | B17: Government Budget Formulation | C17: TRUE
A18: Core Fnancials | B18: Core Financial Execution and Reporting | C18: TRUE
A19: Debt | B19: Public Debt and Guarantee Management | C19: TRUE
A20: Financial Investments | B20: Public Financial Investments | C20: TRUE
A21: Grants | B21: Transfers and Grants | C21: FALSE
A22: Human Resources | B22: Public Service Talent and Capital Human Capital | C22: TRUE
A23: Non-Tax | B23: Revenue and Receipts Mobilization | C23: TRUE
A24: Payroll | B24: Payroll and Wage Bills | C24: TRUE
A25: Performance and Transparency | B25: Fiscal Performance and Transparency | C25: TRUE
A26: Policy Management | B26: Policy Management | C26: FALSE
... A33: Treasury | B33: Treasury and Liquidity | C33: TRUE
A35: Products | B35: =counta(B15:B33) -> 19 | C35: =countif(C15:C33, TRUE) -> 15

Sheet Existing Categories
A1: Categories
A2: LOE Categories
A3: 3rd Party
A4: Integration
A5: Platform
A6: Customer Specific
A7: Services
A8: Suite
A9: New Module
A10: Non-Functional
A11: Report (new GRP Report)
A12: Report (new BIRT Report)
A13: Report (adjustment)

Sheet Concepts
A1: Component Business Model, IBM Approach, Accountability Level | C1: Government Component Mapping, FreeBalance Approach | F1: Component Business Mapping
A2: Direct | B2: Components at this level provide strategic direction and corporate policy to other components. They also facilitate collaboration with other components. | C2: D-AP | D2: Approvals | E2: Process of approving financial management steps | F2: Concept | G2: Explanation
C3: D-PS | D3: Planning & Scenarios | E3: Planning & scenario management | F3: Business Purpose | G3: Why does it exist?
C4: D-RM | D4: Reform & Modernization | E4: Definitions of policy & procedures including legal reform, Chart of Accounts, support for progressive activation | F4: Activities | G4: What simple, cohesive actions are regularly performed?
A5: Control | B5: These mid-tier components serve as checks and balances between the “direct” and “execute” levels. They monitor performance, manage exceptions and act as gatekeepers of assets and information. | C5: C- GC | D5: Government Controls | E5: Budget & commitment controls, approval workflow, segregation of duties | F5: Resources | G5: What tangible assets and human resources are required?
C6: C-ME | D6: Monitoring & Evaluation | E6: Query, analysis, forecasting, visualization | F6: Governance | G6: How are activities and resources managed?
C7: C-PM | D7: Performance Management | E7: Results-based budgeting, value-for-money, merit-based pay, Chart of Goals | F7: Business Services | G7: What is taken from and offered to other components?
C8: C-OA | D8: Oversight & Audit | E8: Oversight agency & audit functionality
A9: Execute | B9: These “boots on the ground” components provide the business actions that drive value creation in the enterprise. They process assets and information for use by other components or the end customer. | C9: E-CM | D9: E-Commerce | E9: Supports online commerce and payments, covering revenue and expenses
C10: E-FT | D10: Fiscal Transparency | E10: Transparency portals, statutory reporting
C11: E-PY | D11: Payments | E11: Supports payments and receipts, including EFT, cheques, cash & other methods not associated with e-commerce.
C12: E-PE | D12: Process Execution | E12: Primarily implements or executes a government financial process
A14: Component business model (CBM) is a technique to model and analyze an enterprise. It is a logical representation or map of business components or "building blocks" and can be depicted on a single page. It can be used to analyze the alignment of enterprise strategy with the organization's capabilities and investments, identify redundant or overlapping business capabilities, analyze sourcing options for the different components (buy or build), prioritizing transformation options and can be used to create a unified roadmap after mergers or acquisitions.

Sheet Pivot Table
A14: PFMCM Components by Pillar
A15: 1. GPM | B15: =M3 -> 67 | C15: =B15/B$23 -> 0.11985689
A16: 2. CBM | B16: =M4 -> 50 | C16: =B16/B$23 -> 0.089445438
A17: 3. PFM | B17: =M5 -> 70 | C17: =B17/B$23 -> 0.12522361
A18: 4. GTM | B18: =M6 -> 64 | C18: =B18/B$23 -> 0.11449016
A19: 5. PEM | B19: =M7 -> 87 | C19: =B19/B$23 -> 0.15563506
A20: 6. GRM | B20: =M8 -> 88 | C20: =B20/B$23 -> 0.15742397
A21: 7. CSM | B21: =M9 -> 107 | C21: =B21/B$23 -> 0.19141324
A22: 8. GSD | B22: =M10 -> 26 | C22: =B22/B$23 -> 0.046511628
B23: =SUM(B15:B22) -> 559 | C23: =SUM(C15:C22) -> 1
A26: PFMCM Components by Type
A27: Control | B27: =sum(B11:E11) -> 143 | C27: =B27/B$30 -> 0.25581395
A28: Direct | B28: =sum(F11:H11) -> 117 | C28: =B28/B$30 -> 0.20930233
A29: Execute | B29: =sum(I11:L11) -> 299 | C29: =B29/B$30 -> 0.53488372
B30: =sum(B27:B29) -> 559 | C30: =B30/B$30 -> 1
D36: =counta(A36:A68) -> 33
A72: COUNTUNIQUE of Function | B72: Type
A73: Pillar | B73: C- GC | C73: C-ME | D73: C-OA | E73: C-PM | F73: D-AP | G73: D-PS | H73: D-RM | I73: E-CM | J73: E-FT | K73: E-PE | L73: E-PY | M73: Grand Total
A74: 1. Government Performance Management | B74: 3 | C74: 2 | D74: 3 | E74: 1 | F74: 4 | G74: 2 | H74: 3 | J74: 4 | M74: 4
A75: 2. Government Compliance Management | B75: 4 | C75: 1 | D75: 3 | E75: 1 | F75: 4 | J75: 4 | K75: 3 | M75: 4
A76: 3. Public Financials Management | B76: 1 | C76: 1 | D76: 2 | E76: 1 | F76: 4 | G76: 2 | H76: 1 | J76: 4 | K76: 3 | M76: 4
A77: 4. Government Treasury Management | B77: 2 | C77: 2 | D77: 3 | F77: 3 | G77: 3 | I77: 1 | J77: 2 | K77: 2 | L77: 1 | M77: 3
A78: 5. Public Expenditure Management | B78: 4 | C78: 3 | D78: 4 | E78: 3 | F78: 4 | G78: 2 | J78: 4 | K78: 4 | M78: 4
A79: 6. Government Receipts Management | B79: 2 | C79: 1 | D79: 3 | F79: 3 | G79: 3 | I79: 3 | J79: 3 | K79: 3 | L79: 2 | M79: 3
A80: 7. Civil Service Management | B80: 3 | C80: 3 | D80: 3 | E80: 1 | F80: 6 | G80: 3 | H80: 1 | J80: 6 | K80: 4 | M80: 6
A81: 8. Government Service Delivery | I81: 3 | J81: 5 | K81: 1 | L81: 5 | M81: 5
A82: Grand Total | B82: 19 | C82: 13 | D82: 21 | E82: 7 | F82: 28 | G82: 15 | H82: 5 | I82: 7 | J82: 32 | K82: 20 | L82: 8 | M82: 33

Sheet Budget 2.0
A1: Budget 2.0
A2: • focus on budget transparency & maturity • updates since original version in green
A4: Concepts
A5: • Budget 1.0: Traditional mechanisms of budget management that are primarily internally-focused (often called “back-office”), where control and compliance are major concerns • Transitional: Increase of externally focused or “front-office” budget management where transparency, web transactions and government reporting are important characteristics but do not achieve “Web 2.0” characteristics • Budget 2.0: Social and Web 2.0 mechanisms that attempt to leverage the network effect to improve government performance and service delivery while leveraging the integration of front and back office systems
A7: Classifications
A8: Transition to Open Government
A9: Classification | B9: Closed: “1.0” | C9: Transition | D9: Open: “2.0”
A10: Transparency | B10: Access to information | C10: Documents | D10: Machine readable
A11: Data Availability | B11: Data for sale | C11: Publish as exception | D11: Publish as norm
A12: Mode | B12: Publish, audit and vetted | C12: Mixed | D12: Near real-time publishing
A13: Target | B13: Business community | C13: Civil society organizations, press | D13: Citizens
A14: Transition to Open Systems
A15: Classification | B15: Closed: “1.0” | C15: Transition | D15: Open: “2.0”
A16: Transition to Open Systems | B16: Vendor Proprietary: Intra-suite integration | C16: Industry standards support with generalized integration points | D16: Service-Oriented Architecture provides ease of integration
A17: Middleware | B17: Vendor Proprietary: customer lock-in | C17: Tactical support for open standards | D17: Full support for open standards, broad open source adoption, availability of low cost cloud deployment services
A18: Extensibility | B18: Vendor proprietary | C18: Vendor eco-system adds value | D18: All vendors and all customers add value
A20: Evaluation
A21: Transparency Mechanisms
A22: Budget 1.0 | C22: Transitional | E22: Budget 2.0
A23: 1 | B23: 2 | C23: 3 | D23: 4 | E23: 5 | F23: 6
B24: Published Documents: Formal documents like “budget book” printed through government printing agency | C24: Web Publishing: Information published to the web as web pages, documents Increasingly pro-active disclosure | E24: Open Data • Pro-active data disclosure, near real-time • Machine-readable information supporting Application Programming Interfaces (APIs) to support information mashups • Increasing amounts of non-financial data including performance information
B25: Narrative-Centric: Documents focused primarily on narrative where diagrams and photographs used to enhance narrative points | D25: Visualization-Centric: Diagrams, charts, multimedia and infographics as primary communications mechanism
C26: Citizen-Centric: Significant effort to provide information so that it is easily understood by citizens
D27: Interactive Data: Search, drill-down, data selection and output
A28: Oversight
A29: Budget 1.0 | C29: Transitional | E29: Budget 2.0
A30: Audit • Primary concern is budget compliance • Often: Internal departmental audit organizations • Often: Independent audit agencies within government | B30: Parliamentary Oversight: Parliamentary budget agencies as counterpoint to government budget organization | E30: Citizen Oversight • Enabled through pro-active disclosure, access to information, open data, machine readable data and mashups • Rise of so-called “data journalism” • Mechanisms to encourage participation including participatory budgeting, crowdsourcing
B31: Audio Visual: Hearings, debates, press conferences published via TV and web
B32: Performance Auditing: Audits matures from budget compliance to performance and risk management
A33: Press and NGO oversight: Freedom of the press and freedom of assembly
C34: Access to information: Freedom of information laws to enable petitioning government for information, formal process to manage, redact and release
B35: Cooperative Planning: Outreach to business, academics, NGOs in planning | D35: Expert Networks: Use of collaborative networks, social media for outreach to communities of experts
A36: Policy Management
A37: Budget 1.0 | C37: Transitional | E37: Budget 2.0
B38: Macro-fiscal frameworks: Methods to collect macroeconomic information and analysis to be used in developing policy | D38: Performance Management • Analysis of policy effectiveness • Results shared externally • Adjustment of programs to better achieve policy objectives | F38: Participatory Policy • Social media mechanisms to develop policy positions during elections • Social media mechanisms to develop policy positions as part of budget formulation process
B39: Policy-budget Linkages: Linkage of policy objectives to budget inputs
C40: Policy Outreach • Leveraging external stakeholders, NGOs, business groups etc. to develop policy • Often: formal methods or public hearings used
A42: Budget Formulation
A43: Budget 1.0 | C43: Transitional | E43: Budget 2.0
A44: Budget as ceremony • Top-down, bottom-up formal and informal processes resulting in budget law • Limited stakeholder engagement outside government & parliament | B44: Budget books • Publication of budget plans, government intentions, organic budget law • Often: pre-budget statement • Often: executive budget proposal | D44: Government Performance Management • Focus on non-financial measures, output and outcome results • Often: use of dashboards and scorecards • Often: performance information published on web • Often: includes accountability structure that enables management discretion, within rules, to optimize performance | F44: Participatory Budgeting: Extends budget preparation to citizens, NGOs, businesses
A45: Budget and Commitment controls • Formalized methods of managing budget and commitment accounting • Matures to aggregate controls, support for decentralized decision-making during budget execution
B46: Program budgeting • Aligns budget with policy • Often: scenario planning and budget assumptions used • Often: first budgets with macro-fiscal frameworks • Often: supports medium-term expenditure framework • Often: procurement planning part of process • Often: project management part of planning | F46: Accrual budgeting • Identifies true value of government investments, liabilities
A47: International Standards
A48: Budget 1.0 | C48: Transitional | E48: Budget 2.0
A49: National Standards • National standardization sets stage for international standards support • Some national standards may be consistent with important characteristics of international standards | B49: IPSAS Cash-Basis • Standardized method enabling comparison among countries • Generally somewhat supported by developed countries • Consistent with IFRS reporting in private sector | D49: Modified Accrual | E49: IPSAS Accrual Basis • More effective government comparison tool • Not yet supported by governments
B50: IMF GFS: Government Financial Statistics supported by many developing countries that may require IMF financing | E50: XML-Based Machine Readable Transparency Standards • IATI International Aid Transparency Initiative • EITI Extractive Industries Transparency Initiative • XBRL eXtensible Business Reporting Language • COST • Open Contracting
B51: Medium Term Expenditure Frameworks • Methodology for developing credible budgets often across three-year window • Typically uses macro-fiscal information as input to budget formulation
A52: Timeliness
A53: Budget 1.0 | C53: Transitional | E53: Budget 2.0
B54: Annual Reports • Annual budget book produced (enacted budget) • Annual audited accounts produced | D54: Unaudited Reports • Periodic reports published before audit | E54: Open Data • Pro-active data disclosure, near real-time • Machine-readable information supporting Application Programming Interfaces (APIs) to support information mashups • Increasing amounts of non-financial data including performance information
C55: In Year Execution • Quarterly or mid-year audited accounts produce
C56: Audit Reports: Audit findings published
C57: Pre-Budget Statement: Budget formulation intentions published in time for parliamentary debate and for citizen engagement
D58: Interactive Data: Search, drill-down, data selection and outputOften: visualization capabilities
A59: Budget Comprehensiveness
A60: Budget 1.0 | C60: Transitional | E60: Budget 2.0
A61: National Government Covers all direct departments and agencies in national government Covers all expenditure and revenue information Often: includes independent and autonomous agencies | B61: Sub-National Integrates all sub-national government information into budget information
B62: Parastatal Integrate all government-owned businesses into budget Extend to support Public Private Partnerships
B63: Accrual Extensions: Asset, property, contingent liability in budget
B64: Information Comprehensiveness Information extends to support: budget preparation, budget execution, government accounts, human resources, procurement, human resources, debt and investment data
A65: Budget Execution and Accounting Methods
A66: Budget 1.0 | C66: Transitional | E66: Budget 2.0
A67: Cash-based Accounting Cash-basis of accounting used | B67: Modified Cash End of year accruals for revenue and expenditures | C67: Modified Accrual Expenditure and revenue accrual | E67: Accrual Accounting Full accrual accounting show full value of government
A68: No commitment controls to line-item budget | B68: Budget and Commitment controls Formalized methods of managing budget and commitment accounting Internal controls includes segregation of duties Matures to aggregate controls, support for decentralized decision-making during budget execution | D68: Program budgeting, cost accounting | E68: Performance Discipline Often: use of dashboards and scorecards Budget execution decisions including budget transfers and virements informed by performance information Risk-based approaches used to make execution decisions
B69: Cash, Liquidity management Adjustment of controls based on cash forecasts including issuing warrants Often: support for Treasury Single Account Often: investment and debt planning
B70: Budget Forecasting Forecasting surplus, deficit situations Use of scenario tools to better predict economic effects to adjust budgets during execution

Sheet Modern Finance Ministry
A1: Modern Finance Ministry
A2: • based on IMF paper in 2015: IMF The Evolving Functions and • extended for FISC 2019
A4: IMF Guiding Principles for the Organization of a Finance Ministry
A5: 1: Unitary finance ministry
A6: 2: Flexible bureaucracy
A7: 3: Agencies to manage specialized finance functions
A8: 4: Devolution of transactional functions to line ministries
A9: 5: Focus on core policy and regulatory functions
A10: 6: Exercise a strong role in agenda setting and shaping policy across the government
A11: 7: Consolidate new functions with existing departments
A13: FreeBalance Finance Ministry Structure
A14: Culture | C14: Ministry beliefs, assumptions, value
A15: Openness | C15: Ministry transparency, collaboration
A16: Focus | C16: Ministry mandate, solution approach
A17: Controls | C17: Organizational Ministry mechanisms
A18: Strategy | C18: Ministry strategic footprint
A19: Orientation | C19: Ministry policy and process orientation
A20: Concern | C20: Drivers for Ministry action
A21: Performance | C21: Ministry performance management practices
A22: Innovation | C22: Adoption methods for Ministry innovation
A24: Finance Ministry Modernization Checklist
A25: • purposely overlap among concepts to better identify gaps • many characteristics will be somewhere in-between full tradition and full modern
A26: Culture
A27: Traditional: Segmentalist | C27: Modern: Integrative
A28: FALSE | B28: Hierarchical decision structures | C28: FALSE | D28: Horizontal coordination decision structures
A29: FALSE | B29: Important decisions with politics | C29: FALSE | D29: Important decisions evidence-driven
A30: FALSE | B30: Decision-making confined to senior levels | C30: FALSE | D30: Decision-making devolved to professional public servants
A31: FALSE | B31: Limited empowerment of Ministry public servants | C31: FALSE | D31: Empowerment of Ministry public servants
A32: FALSE | B32: Organizational silos with functional compartmentalization | C32: FALSE | D32: Program and collaborative organizational culture
A33: FALSE | B33: Leadership “command and control” | C33: FALSE | D33: Balance of top-down & bottom-up leadership
A34: FALSE | B34: Lack of data sharing across Ministry silos | C34: FALSE | D34: Data sharing across Ministry and with other Ministries
A35: FALSE | B35: Unreceptive to ideas outside Ministry | C35: FALSE | D35: Receptive to ideas outside Ministry & government
A36: Openness
A37: Traditional: Closed | C37: Modern: Open
A38: FALSE | B38: Introspective & independent thinking | C38: FALSE | D38: Communicative and interdependent thinking
A39: FALSE | B39: Financial secrecy, concern about stakeholder incentives | C39: FALSE | D39: Sharing information seen as powerful
A40: FALSE | B40: Suspicious of external expertise & information | C40: FALSE | D40: Consultative, open to external expertise & information
A41: FALSE | B41: Protect Ministry by limiting transparency | C41: FALSE | D41: Transparency by default to improve governance outcomes
A42: FALSE | B42: What data is presented in complex, untimely, irrelevant, poor quality | C42: FALSE | D42: HIgh quality timely transparent data presented accessibly
A43: FALSE | B43: Lack of timely communications | C43: FALSE | D43: Timely communications
A44: FALSE | B44: Broadcast communication approach with significant Ministry scrutiny | C44: FALSE | D44: Social media engagement
A45: FALSE | B45: Lack of trust in financial reporting from Ministry | C45: FALSE | D45: Broad trust in financial reporting from Ministry
A46: Focus
A47: Traditional: Inward | C47: Modern: Outward
A48: FALSE | B48: Protective of Ministry mandate & power base | C48: FALSE | D48: Inter-ministerial approach to achieving government goals
A49: FALSE | B49: Limited role in managing tensions across government ministries | C49: FALSE | D49: Manages tensions across government ministries
A50: FALSE | B50: Roles and responsibilities lack clarity or are entirely Ministry focused | C50: FALSE | D50: Roles and responsibilities are clear, used in practice
A51: FALSE | B51: Incentives aligned exclusively to Ministry specialist goals | C51: FALSE | D51: Incentives aligned with broad Ministry & government goals
A52: FALSE | B52: ”Best-practice” solutions approach to public finance | C52: FALSE | D52: Problem-driven approach to public finance
A53: FALSE | B53: Limited legislative scrutiny of budgets, spending or audits | C53: FALSE | D53: Assists legislative scrutiny, educates politicians
A54: FALSE | B54: Financial information provided for scrutiny technical | C54: FALSE | D54: Financial information provided for scrutiny is accessible
A55: FALSE | B55: Poor forecast accuracy | C55: FALSE | D55: Good forecast accuracy
A56: Controls
A57: Traditional: Centralized | C57: Modern: Decentralized
A58: FALSE | B58: Direct control over financial processes | C58: FALSE | D58: Devolved controls over with appropriate discretion
A59: FALSE | B59: Manual approval mechanisms | C59: FALSE | D59: Effective segregation of duties, exception approvals
A60: FALSE | B60: Rigid rules-based approach to setting controls | C60: FALSE | D60: Fiscal risk management approach to setting controls
A61: FALSE | B61: Compliance monitoring | C61: FALSE | D61: Performance monitoring to improve controls
A62: FALSE | B62: Risk-averse to controls changes | C62: FALSE | D62: Efficiency & effectiveness informs controls changes
A63: FALSE | B63: Audits focused on rule compliance | C63: FALSE | D63: Audits focused on performance improvements
A64: FALSE | B64: Cash-based accounting methods | C64: FALSE | D64: Accrual-based accounting methods
A65: FALSE | B65: Controls not integrated across subledgers | C65: FALSE | D65: Controls integrated across subledgers
A66: Strategy
A67: Traditional: Narrow | C67: Modern: Holistic
A68: FALSE | B68: Central government strategic footprint | C68: FALSE | D68: Full public sector strategic footprint
A69: FALSE | B69: Government organizational structure defines strategy | C69: FALSE | D69: Integration with national goals anchors strategy
A70: FALSE | B70: Limited integration with State-Owned Enterprise strategy | C70: FALSE | D70: Tight integration with State-Owned Enterprise Strategy
A71: FALSE | B71: Exchange rate & debt interventions | C71: FALSE | D71: Broad economic interventions
A72: FALSE | B72: Fiscal concerns paramount | C72: FALSE | D72: Country economic concerns paramount
A73: FALSE | B73: Short-term perspective in practice | C73: FALSE | D73: Medium-term perspective in practice
A74: FALSE | B74: Tactical approaches to government fiscal conditions | C74: FALSE | D74: Strategic approach with scenario planning
A75: FALSE | B75: Limited resilience to economic changes | C75: FALSE | D75: Fiscal sustainability built into public finance strategy
A76: Orientation
A77: Traditional: Process | C77: Modern: Policy
A78: FALSE | B78: Finance function centralization regardless of efficiency, effectiveness | C78: FALSE | D78: Finance function decentralization to achieve efficiency, effectiveness
A79: FALSE | B79: Traditional approaches to program funding | C79: FALSE | D79: Modern approaches to program funding
A80: FALSE | B80: Budget inputs focus in budget planning | C80: FALSE | D80: Policy results scenario analysis focus in budget planning
A81: FALSE | B81: Budget plans are incremental | C81: FALSE | D81: Medium-term practice using outcomes in budget planning
A82: FALSE | B82: Organization-structured budget development | C82: FALSE | D82: Program-based budget development
A83: FALSE | B83: Development, operational, salary, debt, capital budgeting not integrated | C83: FALSE | D83: Development, operational, salary, debt, capital budgeting integrated
A84: FALSE | B84: Cash availability approach to payments | C84: FALSE | D84: Cash forecast & liquidity approach to payments
A85: FALSE | B85: Donor funds provided & considered off-budget | C85: FALSE | D85: Donor funds integrated with on-budget funds (country systems used)
A86: Concern
A87: Traditional: Growth | C87: Modern: Wellbeing
A88: FALSE | B88: Revenue collection concerns but high tax avoidance & large informal economy | C88: FALSE | D88: Revenue mobilization designed to demonstrate government value
A89: FALSE | B89: Spending & economic regulation designed to improve GDP growth | C89: FALSE | D89: Spending & economic regulation design for sustainable development
A90: FALSE | B90: Sustainable development goals not integrated with public finance | C90: FALSE | D90: Sustainable development goals integrated with public finance
A91: FALSE | B91: Significant influence of International Financial Institutions on policy | C91: FALSE | D91: Ministry drive International Financial Institutions activities
A92: FALSE | B92: Social public investment like health, education, employment insurance formulaic | C92: FALSE | D92: Social public investment aligned to country social & cultural values
A93: FALSE | B93: Physical public investments affected by political concerns | C93: FALSE | D93: Physical public investments coordinated
A94: FALSE | B94: Disconnected policy, budget planning & budget execution | C94: FALSE | D94: Integrated policy, budget planning & budget execution
A95: FALSE | B95: Ministry mandate disconnected from national goals | C95: FALSE | D95: Ministry mandate aligned with national goals
A96: Performance
A97: Traditional: Fragmented | C97: Modern: Integral
A98: FALSE | B98: Lack of performance structures | C98: FALSE | D98: Performance structures like balanced scorecard used
A99: FALSE | B99: Ministry performance unaligned with government goals | C99: FALSE | D99: Performance aligned with government goals, extended across all finance functions
A100: FALSE | B100: Performance measures complex, unclear or unrelated to outcomes | C100: FALSE | D100: Simple, clear, rational & measurable outputs & outcomes
A101: FALSE | B101: Primary use of complex reporting for decision-makers | C101: FALSE | D101: Analytical integration & modeling with visualization methods used
A102: FALSE | B102: Lack of value analysis for public investments | C102: FALSE | D102: Value for money & cost-benefit analysis for public investments
A103: FALSE | B103: Limited use, or no use of program budgeting | C103: FALSE | D103: Program & performance budgeting operating in practice
...

Sheet COFOG
A1: United Nations Classification of the Functions of Government COFOG
A2: First Level | B2: Second Level | C2: =counta(B3:B71) -> 69
A3: 01 - General public services | B3: 01.1 - Executive and legislative organs, financial and fiscal affairs, external affairs
A4: 01 - General public services | B4: 01.2 - Foreign economic aid
A5: 01 - General public services | B5: 01.3 - General services
A6: 01 - General public services | B6: 01.4 - Basic research
A7: 01 - General public services | B7: 01.5 - R&D General public services
A8: 01 - General public services | B8: 01.6 - General public services n.e.c.
A9: 01 - General public services | B9: 01.7 - Public debt transactions
A10: 01 - General public services | B10: 01.8 - Transfers of a general character between different levels of government
A11: 02 – Defence | B11: 02.1 - Military defence
A12: 02 – Defence | B12: 02.2 - Civil defence
A13: 02 – Defence | B13: 02.3 - Foreign military aid
A14: 02 – Defence | B14: 02.4 - R&D Defence
... A71: 10 - Social protection, | B71: 10.9 - Social protection n.e.c.

Sheet Treasury Reference Model
B1: World Bank Treasury Reference Model, 2001
B2: Subordinate Units | C2: Spending & Revenue Collection Agencies | D2: MoF Budget Accounting | E2: MoF Cash Management | F2: MoF Debt Management | G2: MoF Budget Management | H2: Central Bank | I2: Commercial Banks | J2: Donor Agencies | K2: Taxpayers
A3: 1. Budget Authorization Management | B3: Record, receive | C3: Budget allotments | G3: Budget, allocations, appropriations
B4: Record, receive | C4: Sub-warrants | G4: Warrant allocations
A5: 2. Commitment of Funds | B5: Permission to commit | C5: Approve | D5: Record in system | E5: Cash position | G5: Revised limits & warrants
A6: 3. Payments and Receipts Management | B6: Goods receive
A7: 3.1 Payments | B7: Request for payment | C7: Approve | D7: Record in system | E7: Payment instructions | H7: Payments to creditors | I7: Receive, record
A8: 3.2 Receipts | B8: Review, reconcile | C8: Review, reconcile | D8: Record in system | H8: Receipts deposit | I8: Tax, non-tax receipts | K8: Tax, non-tax receipts
A9: 4. Cash Management | B9: Cash & revenue forecasts | C9: Review, consolidate | E9: Prepare overall cash requirements | F9: Debt service | H9: Cash balances
A10: 5. Debt and Aid Management
A11: 5.1 Debt Management | C11: Record & monitor | D11: Loans, grants, in-kind receipts | F11: Record, receive new debt | G11: Review, revise limits, warrants, borrowing req's | H11: Loan & grant agreements
A12: 5.2 Aid Management | C12: Record & monitor | D12: Loans, grants, in-kind receipts | F12: Record, receive new aid | J12: Aid agreements
A13: 6. Budget Review and Fiscal Reporting
A14: 6.1 Budget Review | G14: Budget reviews, revise limits and warrants
A15: 6.2 Fiscal Reporting | B15: Project, program status reports | C15: Project, program status reports | D15: Overall revenue & expenditure position | G15: Fiscal Reports

Sheet FMIS
A1: World Bank FMIS Core/Non Core
A2: F: FMIS Core | B2: T: Treasury Systems | C2: General Ledger
C3: Accounts Payable
C4: Accounts Receivable
C5: Commitment Management
C6: Cash Management
C7: Financial Reporting
D8: • management of budget authorizations/releases
D9: • commitment of funds
D10: • payment/revenue management (mostly based on treasury single account)
D11: • cash forecasting and management
D12: • accounting and reporting
B13: B: Budget Systems | C13: Budget Formulation
C14: Public Investment Management
D15: • medium term frameworks (e.g. MTFF, MTBF, MTEF)
D16: • program based budgeting
D17: • performance informed budgeting
A18: O: Other | C18: Personnel management
C19: Payroll
C20: Revenue Administrations (Tax and Customs)
C21: Public procurement
C22: Inventory Management
C23: Debt Management
C24: Property Management
C25: Performance Monitoring
D26: • revenue collection (mainly interfaces with tax and customs systems)
D27: • debt management (covering both domestic and external debt)
D28: • procurement/purchasing (tracking all payments after contract signature)
D29: • asset and inventory management
D30: • Human Resources Management Information System (HRMIS)
A31: P: Prepatory Work | B31: For T or F | D31: • accounting/financial reporting reforms, including compliance with International Public Sector Accounting Standards (IPSAS)
D32: • budgeting and macro-economic forecasting in the Ministry of Finance/Economy
D33: • establishment of Treasury Single Account (TSA)
D34: • improvement of budget classification (BC) and unified chart of accounts (CoA)
A35: B: Beyond FMIS | B35: typically outside FMIS | C35: Policy Development and Review
C36: Publishing/Web Portal
C37: Audit and Evaluation

Sheet IMF Budget Cycle
A1: IMF Budget Cycle
A2: 0. Legal Framework | B2: • Developing Legal Frameworks To Promote Fiscal Responsibility
A3: 1. Fiscal Framework | B3: • Integrating Fiscal Risk Management into the Budget Cycle • The Design of National Fiscal Frameworks and their Budgetary Impact
A4: 2. Budget Preparation | B4: Guidelines for Public Expenditure Management • Introduction • The Expenditure Aggregates and Data Sources • Budget Preparation
A5: 3. Budget Execution | B5: Guidelines for Public Expenditure Management • Budget Execution • Cash Planning and Management
A6: 4. Accounting and Reporting | B6: • Budgeting, accounting, and reporting • Government Budget and Accounting Systems
A7: 5. Control and Audit | B7: • Expenditure Control: Key Features, Stages, and Actors

Sheet International Assessments
A1: International Public Finance Assessments
A3: Public Expenditure and Financial Accountability (PEFA)
A4: Pillar | B4: Performance Indicator
A5: I. Budget Reliability | B5: PI - 1. Aggregate expenditure outturn
B6: • 1.1 Aggregate expenditure outturn
B7: PI - 2. Expenditure composition outturn
B8: • 2.1 Expenditure composition outturn by function • 2.2 Expenditure composition outturn by economic type • 2.3 Expenditure from contingency reserves
B9: PI - 3. Revenue outturn
B10: • 3.1 Aggregate revenue outturn • 3 .2 Revenue composition outturn
A11: II. Transparency of Public Finances | B11: PI - 4. Budget classification
B12: • 4.1 Budget classification
B13: PI - 5. Budget documentation
B14: • 5.1 Budget documentation
B15: PI - 6. Central government operations outside financial reports
B16: • 6.1 Expenditure outside financial reports • 6.2 Revenue outside financial reports • 6.3 Financial reports of extrabudgetary units
B17: PI - 7. Transfers to subnational governments
B18: • 7.1 System for allocating transfers • 7.2 Timeliness of information on transfers
B19: PI - 8. Performance information for service delivery
B20: • 8.1 Performance plans for service delivery • 8.2 Performance achieved for service delivery • 8.3 Resources received by service delivery units • 8.4 Performance evaluation for service delivery
B21: PI - 9. Public access to fiscal information
B22: • 9.1 Public access to fiscal information
A23: III. Management of Assets and Liabilities | B23: PI - 10. Fiscal risk reporting
B24: • 10.1 Monitoring of public corporations • 10.2 Monitoring of subnational governments • 10.3 Contingent liabilities and other fiscal risks
B25: PI - 11. Public investment management
B26: • 11.1 Economic analysis of investment proposals • 11.2 Investment project selection • 11.3 Investment project costing • 11.4 Investment project monitoring
B27: PI - 12. Public asset management
B28: • 12.1 Financial asset monitoring • 12.2 Nonfinancial asset monitoring • 12.3 Transparency of asset disposal
B29: PI - 13. Debt management
B30: • 13.1 Recording and reporting of debt and guarantees • 13.2 Approval of debt and guarantees • 13.3 Debt management strategy
A31: IV. Policy-based Fiscal Strategy & Budgeting | B31: PI - 14. Macroeconomic and fiscal forecasting
B32: • 14.1 Macroeconomic forecasts • 14.2 Fiscal forecasts • 14.3 Macrofiscal sensitivity analysis
B33: PI - 15. Fiscal strategy
B34: • 15.1 Fiscal impact of policy proposals • 15.2 Fiscal strategy adoption • 15.3 Reporting on fiscal outcomes
B35: PI - 16. Medium-term perspective in expenditure budgeting
B36: • 16.1 Medium-term expenditure estimates • 16.2 Medium-term expenditure ceilings • 16.3 Alignment of strategic plans and medium-term budgets • 16.4 Consistency of budgets with previous year’s estimates
B37: PI - 17. Budget preparation process
B38: • 17.1 Budget calendar • 17.2 Guidance on budget preparation • 17.3 Budget submission to the legislature
B39: PI - 18. Legislative scrutiny of budgets
B40: • 18.1 Scope of budget scrutiny • 18.2 Legislative procedures for budget scrutiny • 18.3 Timing of budget approval • 18.4 Rules for budget adjustment by the executive
A41: V. Predictability & Control in Budget Execution | B41: PI - 19. Revenue administration
B42: • 19.1 Rights and obligations for revenue measures • 19.2 Revenue risk management • 19.3 Revenue audit and investigation • 19.4 Revenue arrears monitoring
B43: PI - 20. Accounting for revenue
B44: • 20.1 Information on revenue collections • 20.2 Transfer of revenue collections • 20.3 Revenue accounts reconciliation
B45: PI - 21. Predictability of in-year resource allocation
B46: • 21.1 Consolidation of cash balances • 21.2 Cash forecasting and monitoring • 21.3 Information on commitment ceilings • 21.4 Significance of in-year budget adjustments
B47: PI - 22. Expenditure arrears
B48: • 22.1 Stock of expenditure arrears • 22.2 Expenditure arrears monitoring
B49: PI - 23. Payroll controls
B50: • 23.1 Integration of payroll and personnel records • 23.2 Management of payroll changes • 23.3 Internal control of payroll • 23.4 Payroll audit
B51: PI - 24. Procurement
B52: • 24.1 Procurement monitoring • 24.2 Procurement methods • 24.3 Public access to procurement information • 24.4 Procurement complaints management
B53: PI - 25. Internal controls on non salary expenditure
... B56: • 26.1 Coverage of internal audit • 26.2 Nature of audits and standards applied • 26.3 Implementation of internal audits and reporting • 26.4 Response to internal audits
A57: VI. Accounting & Reporting | B57: PI - 27. Financial data integrity
B58: • 27.1 Bank account reconciliation • 27.2 Suspense accounts • 27.3 Advance accounts • 27.4 Financial data integrity processes
B59: PI - 28. In-year budget reports
B60: • 28.1 Coverage and comparability of reports • 28.2 Timing of in-year budget reports • 28.3 Accuracy of in-year budget reports
B61: PI - 29. Annual financial reports
B62: • 29.1 Completeness of annual financial reports • 29.2 Submission of reports for external audit • 29.3 Accounting standards
A63: VII. External Scrutiny & Audit | B63: PI - 30. External audit
B64: • 30.1 Audit coverage and standards • 30.2 Submission of audit reports to the legislature • 30.3 External audit follow-up • 30.4 Supreme Audit Institution independence
B65: PI - 31. Legislative scrutiny of audit reports
B66: • 31.1 Timing of audit report scrutiny • 31.2 Hearings on audit findings • 31.3 Recommendations on audit by the legislature • 31.4 Transparency of legislative scrutiny of audit reports
A68: Climate-Responsive PEFA
A69: Item | B69: Performance Indicator
A70: 1 | B70: Budget alignment with climate change strategies
A71: 2 | B71: Tracking climate-related expenditure
A72: 3 | B72: Climate-responsive budget circular
A73: 4 | B73: Legislative scrutiny
A74: 5 | B74: Climate-responsive public investment management
A75: 6 | B75: Climate-responsive non-financial asset management
A76: 7 | B76: Climate-related liabilities
A77: 8 | B77: Climate-responsive public procurement
A78: 9 | B78: Climate-responsive tax administration
A79: 10 | B79: Compliance of climate-related expenditure
A80: 11 | B80: Climate-responsive fiscal decentralization
A81: 12 | B81: Climate-related performance information
... A83: 14 | B83: Expenditure outturn for climate actions
A85: Gender-Responsive PEFA
A86: Item | B86: Performance Indicator
A87: 1 | B87: GRPFM–1 Gender impact analysis of budget policy proposals
A88: 2 | B88: GRPFM–2 Gender responsive public investment management
A89: 3 | B89: GRPFM–3 Gender responsive budget circular
A90: 4 | B90: GRPFM–4 Gender responsive budget proposal documentation
A91: 5 | B91: GRPFM–5 Sex-disaggregated performance information for service delivery
A92: 6 | B92: GRPFM–6 Tracking budget expenditure for gender equality
A93: 7 | B93: GRPFM–7 Gender responsive reporting
A94: 8 | B94: GRPFM–8 Evaluation of gender impacts of service delivery
A95: 9 | B95: GRPFM–9 Legislative scrutiny of gender impacts of the budget
A97: Debt Management Performance Assessment (DeMPA)
A98: Pillar | B98: Performance Indicator
A99: Governance and Strategy Development | B99: DPI-1 Legal Framework
B100: DPI-2 Managerial Structure
B101: DPI-3 Debt Management Strategy
B102: DPI-4 Debt Reporting and Evaluation
B103: DPI-5 Audit
A104: Coordination with Macroeconomic Policies | B104: DPI-6 Coordination with Fiscal Policy
B105: DPI-7 Coordination with Monetary Policy
A106: Borrowing and Related Financing Activities | B106: DPI-8 Domestic Borrowing
B107: DPI-9 External Borrowing
...

Sheet CIPFA Whole Systems Approach
A1: CIPFA: Public Financial Management: A Whole Systems Approach
A2: Legislation | B2: the regulatory framework for PFM, determining the powers and mandatory requirements within which public sector bodies raise and spend money and receive income. Legislation should be transparent and its application predictable, so that it can be consistently administered and can be navigated by civil society.
B3: L1: Taxation raising powers | C3: the national government’s definition of the powers to raise taxation to fund public expenditure. The taxes available to each level of administration may differ, for example between national, regional or local government. There may also be a variety of taxation sources available, e.g. assigned or hypothecated taxation revenues, or a mixture, such as property taxes, sales taxes, tourism taxes, vehicle registration charges. The powers to levy local taxes may also be limited by national or regional government.
B4: L2: PFM Legislation | C4: the powers and limits of operation granted by statute, including over budgets, charging and spending. This may also include requirements to adopt practices that are to be set out in standards.
B5: L3: Funding conditions | C5: the terms on which funds may be received and applied, whether external aid or, within a country, specific subsidy. These are binding in that spending that falls outside these terms is liable to be repaid
B6: L4: Accounts and audit requirements | C6: the government’s prescription of essential elements of accounting and auditing in the public sector – for example, the duty to maintain a system of internal control and internal audit, to maintain accounting records, and the content, approval and publication of the accounts, the rights of the public in relation to the accounts and the external auditor’s report. Regulations may also prescribe the individual duties of statutory posts and the professional standards to be adhered to.
B7: L5: Public access to information | C7: requirements that define public rights to access information held by public sector organisations. Such rights and protocols support openness, accountability and equity. Information about high level budgets, outturn, financial statements and major contracts lay the foundation for civil scrutiny. Other areas of administrative law may also have a particular bearing on PFM.
A8: Standards | B8: the established principles or rules common to a group of like organisations or professionals that is intended to govern their actions and behaviour to achieve compliance with a common set of non-statutory requirements. Observation of standards is likely to be on a ‘comply or explain’ basis, and unjustified breaches can attract investigation and discipline, which may result in sanctions. Standards may be developed internationally by bodies such as the International Federation of Accountants (IFAC) and CIPFA, by national governments and professional bodies or on a sectoral basis within a jurisdiction.
B9: S1: Principles of public administration | C9: principles that set out the standards expected of public officials help to underpin the effectiveness of organisations and will also bear on their financial management. Principles may relate to behaviour (e.g. integrity, objectivity, openness, honesty, leadership by example), to management practice and accountability, or to the professionalism and pay of the civil service itself. In some countries such principles are set out through legislation
B10: S2: Governance Standards | C10: good governance in the public service requires a focus on the organisation’s purposes and its intended social outcomes. It also carries an obligation to be accountable to citizens, taxpayers and service users and to make best use of resources and ensure value for money. Financial management is therefore a core corporate discipline, that should be reflected in an overall corporate governance framework that covers all the entity’s activities (financial and non-financial). Aspects specifically relevant to PFM are the duty of public service leaders to determine the allocation of resources, to manage resource use and performance objectives, to maintain a system of controls, to assess and manage risk, to uphold high standards of behaviour, to take informed and transparent decisions which are subject to scrutiny, to develop capacity and capability across the organisation and to engage with stakeholders to ensure public accountability
B11: S3: Codes of conduct | C11: within the general principles of public life there are likely to be specific codes governing the conduct of elected office holders, public sector employees and qualified professionals.
B12: S4: Accounting Standards | C12: accounting standards help to ensure consistency and comparability, and improve the reliability of financial information for its national and international users. The International Public Sector Accounting Standards Board (IPSASB) promulgates accounting standards for the public sector. Its goals are “to serve the public interest by developing high quality accounting standards for use by the public sector entities around the world in the preparation of general purpose financial statements. This will enhance the quality and transparency of public sector financial reporting and strengthen public confidence in public sector financial management.”2 Standards may be set at the national level. They can sometimes be geared towards the private sector and may need to be translated for the public service context. It is widely recognised that implementing sophisticated standards, such as the International Financial Reporting Standard, can be very difficult for many developing countries and the appropriate path is much debated.
B13: S5: Auditing standards | C13: Audit bodies such as INTOSAI issue specific topic standards. Standards for auditors are likely to cover the following general issues: • Auditors’ competence and training, professionalism, including exercising due care, understanding the business of the entity that they audit, being objective and independent. • Field work: planning and managing audits, use of risk assessment techniques, evidence gathering, documentation and quality assurance. • Reporting: content required to report on, (e.g. external audit must report on financial statements and legal compliance); to whom they report, whether there are special circumstances, such as a report in the public interest
B14: S6: Budget classification and/or standard chart of accounts | C14: standardisation of the principal headings under which expenditure and income is grouped helps to aggregate, analyse and exchange financial information in a meaningful way. A chart of accounts will typically show allocations to spending unit, function, economic activity and programme and may also allow some locally defined detail. Classifying budgets and expenditure is a foundation for collecting and publishing information about the public sector and for enabling accountability and public discourse. Use of a uniform structure at sub-national level will be necessary to produce consolidated government accounts.
B15: S7: Role of the Chief Financial Officer | C15: the CFO is the term used for the organisation’s most senior executive role charged with leading and directing financial strategy and operations. This role and its responsibilities should be set out through employment terms. There are common insights into how that role can be made most effective. Codification can help to enable a shared understanding of the role and create the conditions for organisational effectiveness and accountability. The CFO should have a relevant qualification, exercise a professional duty of care and adhere to a code of ethics. The CFO’s activities are likely to include formulating a financial strategy that underpins the organisation’s goals and enables its financial health in the short, medium and long term, acting as financial advisor and technical expert for the organisation and responsibility for financial administration.
A16: Execution: Strategy & Planning | B16: the processes that set the direction for the activities which require financial management, in the short, medium and longer term, and the frameworks within which overall financial performance is managed.
B17: SP1: Funding Coherence | C17: the credibility of the budget is underpinned by secure flows of funds from the organisation controlling the source of funds. This applies where governments are allocating resources and for countries receiving donor aid. Funding transfers ought to be predictable as to amount and timing, and the calculation of allocations should be rational and explicable. Vertical allocation, e.g. to sub-national agencies, is likely to be policy led, and horizontal allocation, for example, amongst local government bodies, should be principles based, following objective criteria or formulae. The amount that is ring fenced to specific purposes, or provided off-budget should be limited, in order not to distort the spending body’s own priorities, although different tolerances may apply to major infrastructure projects. Where funding comes from a combination of sources there should be co-ordination between the different funders.
B18: SP2: Option appraisal and prioritisation | C18: the relative merits of spending on recurrent or investment options should be appraised in a structured way, comparing their benefits, costs and rates of return over the whole life of the project, using appropriate techniques.4 Comparative rates of return are relevant to decisions about public versus private investment generally, not only for comparison between individual projects. Prioritisation, based on a sound analysis of costs and benefits, is essential for securing value for money, for allocating resources efficiently and for establishing a realistic project budget that can be managed effectively.
B19: SP3: Funding sustainability strategy | C19: medium and long term resource planning should be informed by a forward projection of liabilities and the capacity to meet them from projected revenue sources. The aim should be to develop a sustainable funding strategy that supports future expenditure and liabilities, including those that may be outside the balance sheet, such as private finance initiative commitments or pensions liabilities. The strategy will need to consider issues such as solvency, variation in the tax base, inter-generational equity, and stability of taxation levels5. The projections should also take account of risk assessment and sensitivity testing, e.g. risks to future grant levels, or to taxation dependent on levels of economic activity.
B20: SP4: Integrated policy & financial strategy: Medium Term Expenditure Framework | C20: brings together fiscal targets and strategic policy priorities in a transparent and accountable planning process for three or more years ahead. Its core purpose is to create a coherent expenditure framework that links forward and recurrent expenditures into an agreed financial aggregate6 and enables policy plans to be reconciled with available resources and affordability. A highly developed process will also be based on horizon scanning, so that it takes account of external forces that will shape future plans, such as new legislation, demographic change affecting service demand, and social or technology change. It would integrate policy planning and performance with financial planning, and recurrent budgets with project budgets. Policy plans should be grounded in a review of past and existing expenditure and income patterns, with projections of future spending, and be supported by realistic funding forecasts and strategies. Where relevant, it should include external donor aid so that these objectives are integrated into budgets and are monitored consistently with other plans. Risk analysis and scenario testing can help to deal with the unavoidable uncertainty of forward projections and risk management techniques are likely to be required for economic and fiscal risks that can destabilise the MTEF realisation. The MTEF’s value as a planning and accountability document is enhanced if future funding is predictable, but it can be hard to sustain at times of economic or other turbulence in the planning environment. The MTEF is a strategic tool for governments, but lower tier public service organisations should also develop a proportionate medium term financial strategy that integrates and trades off service priorities and affordability within a corporate planning process
B21: SP5: Integrating policy & shorter term financial planning | C21: the processes that apply to medium term strategy also apply to shorter tem planning, resolving the allocation of resources in the light of competing policy priorities, spending pressures, savings opportunities, risk assessment and funding proposals. Medium term commitments implied by annual plans should form part of forward projections.
B22: SP6: Budget preparation (revenue and capital) | C22: budget documents are the financial expression of service plans and they set the limits of expenditure authorisations for managers. Externally, annual plans should explain transparently the economic assumptions, e.g. inflation, and how the organisation is allocating resources between different services and programmes. Presentation should include summary budgets compared with the previous year’s actual expenditure, current year and the next year’s plans and explain major changes. Budgets should show functional expenditure gross with income detailed separately and should also identify the funding plan, detailing the source of funds. Budgets should be legal, realistic and based on robust assumptions and calculations, so that they are realistic targets for spending managers, and to minimise disruptive in-year adjustments. They should be comprehensive, with minimal off-budget expenditure, so that they form part of the overall fiscal policy framework and are subject to the same disciplines of monitoring and reporting. Funders are aware that budget predictability benefits service planning. Detailed service budgets should explain allocations to individual services and be the basis for managers to operate throughout the year, with managers clear about the budget rules and the scope of their authority to spend. Individual spending units should have an opportunity to input to budget preparation, to strengthen credibility, and should be notified of their budget allocations before the year begins, so that they can plan their commitments and fulfil their policy goals.
B23: SP7: Finance for service decision makers | C23: financial information needs to support the needs of policy makers, planners and service managers, not just the financial experts. Managers need information based on calculating and interpreting cost drivers and trends, extrapolating forecasts, unit costs, variances and sensitivities. They need the skills to understand the financial implications of potential decisions so that they can manage risks, deliver value for money, make use of opportunities and take action to stay on budget. Management accounting helps managers to prioritise investment and is especially relevant in devolved environments.
B24: SP8: Costing & pricing/ charginig/subsidising | C24: understanding the unit costs of activities and projects enables organisations to allocate resources more efficiently and to forecast the impact of demand variation. Finance professionals need to be competent to select and use appropriate costing techniques and to analyse and interpret costs, so that they can advise managers. Organisations should also consider when services will be free or subsidised and when charges will recover service costs or will even generate a profit that can cross subsidise other activities or client groups. The design of charges and income collection processes should be efficient, and arrears actively pursued.
B25: SP9: Balance sheet management | C25: information on assets, cash, debt, contingent liabilities and planned capital expenditure is necessary to ensure long term fiscal sustainability. A structured approach to managing balance sheet asset and liabilities helps to ensure that resources are being used effectively, both financially and operationally, that the future impact of changes in assets and liabilities is considered, and that appropriate governance arrangements are in place to demonstrate stewardship in the use of public sector assets. The balance sheet also shows the quality of financial standing and the capacity for investment.
B26: SP10: Managing assets productively | C26: public sector bodies are often extremely large property owners, so they have a responsibility for ensuring that assets are fit for their public purpose and are adequately maintained. Holding assets, whether property, IT or equipment, ties up cash and incurs running costs. So assets need to be managed, examining how they drive future costs, their importance for business continuity, their maintenance and replacement planning, their utilisation and opportunities for greater productivity, rationalisation and disposal.
A27: Execution: Operations | B27: the principal financial operations needed to maintain financial discipline and resilience, deliver services and enable desired outcomes. Monitoring of the Paris Declaration’s commitment to using country systems focuses on national budgeting and accounting systems in this area. In practice, while central governments may set the framework for spending, it will often be departmental ministries and local administrations who carry it out. It is important to consider the whole range of operations and the level at which they are undertaken in order to plan and create capacity building initiatives.
B28: O1: Budget execution | C28: delivering the budget as planned, against service analysis as well as aggregate totals, supports realisation of policy goals, while resource control underpins credibility. This relies on processes to track commitments and manage resources without overspending, which can destabilise other spending plans. The quality of expenditure is also important, and managers should try to achieve value for money, avoiding unnecessary spending, ensuring they buy at good prices, and manage staffing budgets carefully
B29: O2: Procurement | C29: the process of acquiring goods, construction works and services. It is concerned with obtaining the best services, supplies and works to meet the needs of the purchasing organisation at a price it is prepared to pay. It therefore involves understanding service needs, understanding the market and applying sound processes and complying with relevant legislation. Procurement spans the whole cycle from identification of needs, commissioning, specifying, tendering, letting and then managing a contract through to contract end or the end of an asset’s useful life and its disposal. Although it is a full topic on its own, ensuring strong procurement arrangements is also integral to PFM: • Appraising and selecting appropriate procurement strategies, considering their resource implications (e.g. whether to do something in-house or to buy in goods, whether to lease or purchase, whether to use Public Private Partnerships). • Ensuring probity and propriety in spending money on goods and services through establishing and monitoring transparent authorisation and contract procedures, and maintaining records, guarding against loss, fraud and corruption. • Ensuring value for money, for example, through competition and contestability, accessing wide markets, supply chain management, supplier relationships and market management/development. • Ensuring value for money during the life of a contract through effective contract management and performance monitoring, and through opportunities for improved methods during long life contracts. • Ensuring efficiency through contracting arrangements, e.g. using framework and consortium contracts and exploiting economies of scale by aggregating purchasing power and market influence. Off contract purchasing should be minimised. • Ensuring efficient and low cost financial administration and transactions for example by automated purchase to pay processes, or electronic tendering, where feasible. • Ensuring that the public sector captures the value of assets that are disposed of.
B30: O3: Financial transactions revenues, payments, payroll, pensions administration | C30: revenues, payments, payroll and pensions administration are specialised key financial processes each requiring management through performance indicators that measure unit costs, trends, accuracy and timeliness. Because of the volumes of transactions and the sums involved internal controls should be tight and are likely to be audited annually.
B31: O4: Revenue collection | C31: spending plans can depend on effective revenue collection. The assessment basis for taxation and other sources of revenue should be based on clear general rules, and the amount, time and manner of payments should be clearly set out. The registration, assessment, and payment processes should be efficient, so that high collection rates can be achieved and the cost of collection is proportionate to the yield. This will be backed by public information programmes, processes to pursue arrears promptly and controls that incentivise compliance, such as penalties and investigations.
B32: O5: Treasury management | C32: debt and long term capital financing, investments, cash management: the sums involved, and the long term financial implications, mean that risk management, internal controls and regulatory arrangements need to be strong, and agreed at very senior executive level. Information on long term debt commitments (or their equivalent e.g. private finance liabilities) is necessary for prudential planning, to ensure that policies remain affordable. Complex or innovative funding arrangements will require specialist advice that may well not exist inside individual organisations. Specialist treasury management policies and practices must focus on securing a return compatible with the security of the capital sum. Reliable cash flow forecasts will help to plan debt and treasury activity and to ensure that budgets are not unexpectedly adjusted during the year. Debt and investment activity will be supervised by national government bodies, and they will also play a part in the provision of capital and cash management facilities in the public sector
B33: O6: Accounting | C33: records expenditure and income (or receipts and payments in countries not yet using accrual systems) by type of expenditure and by activity, comparing actual records against budgeted allocations. It also includes measuring and recording the value of assets and liabilities. Accurate, timely and reliable financial information is required to understand and calculate costs, analyse trends and support decision making and financial control. Accounting information is also necessary to plan realistically how resources are allocated to policies, programmes and services, to assess relative value for money and to give an account of expenditure and income to citizens and other stakeholders
B34: O7: Financial management information systems | C34: usually refers to computerized budgeting, accounting and payment operations, though the hallmarks of a good system apply equally to non IT applications. Systems output should be accurate, reliable and timely, and present information that is relevant and meets the straightforward needs of users, with little additional manipulation. IT systems need to be documented, well maintained, and users need to be trained.
B35: O8: Reporting | C35: reporting and publishing budget and accounts information clearly and objectively, in a variety of forms suitable for different audiences (whether citizens, government or donors) is a primary accountability function. Accountability generally should be a lever to make better use of resources. In relation to annual financial accounts it can be reinforced by public rights to inspect items of account, to lodge objections with auditors, and by publication of external audit reports. As well as reporting annual financial results in the statement of accounts and annual report, organisations will also compile in-year summary information as part of their accountability to government and other funders, enabling aggregate fiscal risks to be monitored. Informative reporting that can be used by citizen groups and the media as a lever to reform can be especially significant in the developing world where public information may be hard to access and interpret.
A36: Execution: Monitoring & Internal Control | B36: a cluster of processes, complementary to operations, designed to measure progress and achievement of milestones and to keep organisations on track to realise their objectives. They constitute a framework for activity, that manages risk and prompts corrective action if forecast results deviate from plans. Internal controls aim to ensure that resources are directed towards planned purposes with as little leakage as possible. Internal controls need to be designed into organisational processes – and are therefore distinct from internal audit, which aims to provide assurance that processes are effective, efficient and economical and to check that control and feedback mechanisms add value. Regular in-year monitoring of performance and related financial transactions by finance and service delivery teams, working together, allows organisations to understand their financial position and their progress towards service goals, and enables management to make proactive adjustments if they believe variations will prejudice results or financial sustainability. Sound internal control is a platform for delegation and management accountability
B37: MC1: Financial performance management | C37: budget management is directed to financial flows but also to monitoring that the expected performance from using resources is being measured and achieved.
B38: MC2: Budget monitoring & management | C38: spending units should receive reliable in-year budget reports in a timely way. Monitoring should aim for ‘no surprises’. It should be forward looking, focussed on large or important items and track lead operational indicators as well as time lagged financial records. Budget reports should be timely and should explain clearly to decision makers the financial position and consequent options, so that corrective action can be taken in good time if necessary. Budget management during the year should enable outturn expenditure to match original budgets, in order to reflect original policy plans. Lessons learned from monitoring (as well as audit) should be absorbed and disseminated for future use in subsequent budget cycles.
B39: MC3: Financial risk management | C39: applies general risk management processes in the PFM context both to strategic financial planning and to operational activity. This implies a logical and systematic method of establishing the context, identifying, analysing, evaluating, treating and monitoring the financial risks associated with any activity, function or process in a way that will enable an organisation to minimise losses and maximise opportunities. Where supported by analysis and an understanding of the likelihood of consequences, trading off impact and probability, it helps to determine the acceptable level of risk (risk appetite) and how it can be economically managed. Risk can be accepted or mitigated but is unlikely to be eliminated. In the aid context fiduciary risk assessment, trading off risk and reward, is an important discipline. For countries it is also necessary to monitor the fiscal risk that can result from the actions of sub- or supranational organisations.
B40: MC4: Internal financial control safeguards | C40: internal financial control safeguards are control systems established by management to help ensure that an organisation achieves its objectives in a manner that promotes economical, efficient and effective use of resources and safeguards its assets and interests. These controls should be risk proportionate. They include ensuring legal compliance, physical security of assets, and procedures such as accounting and bank reconciliations, clearance of suspense accounts, separation of duties, audit trails and regular checks that help to prevent problems, identify if things go wrong and prompt early action.
B41: MC5: Fraud and corruption: prevention detection and investigation | C41: prevention, investigation and detection are important aspects of the stewardship of public resources, whether fraud and/or corruption are suspected within an organisation or are being practised upon an organisation. Investigation requires somewhat different skills and techniques from an audit investigation, for example in understanding the legal and ethical framework, securing evidence, interviewing and preparing prosecution. National and international (for example EU) institutions can play a significant role in addressing money laundering, and in coordinating anti-fraud data matching, together with its legal frameworks and protocols.
B42: MC6: Internal financial regulations | C42: the framework, internal to an organisation, for managing its financial arrangements. Regulations set out the delegations, authorisations, responsibilities, freedoms and disciplines applicable to all those who take action on the organisation’s behalf. That includes line managers who take decisions with financial implications, not just finance staff, so they should be well understood and promoted throughout the organisation. Breaches of regulations may result in disciplinary action. Regulations should cover principal financial activities, such as budgeting and committing expenditure, in-year monitoring, the duty to consider financial implications and take appropriate advice, year end carry forward and virement tolerances, accounting, treasury management, payroll, payments and income controls, bad debt and write off authorisations, treatment of grants and external funding, safeguarding of assets, work for outside bodies, authority to enter into financial partnerships and audit’s access to records, information and staff
B43: MC7: Operating manuals | C43: internal systems and processes should be documented to record and guide proper operations, to help establish internal control safeguards and as a reference for staff and auditors in their day to day work. Well documented procedures help to stop drifts that can jeopardise internal controls, and are an important part of business continuity when staff change.
B44: MC8: Internal procurement regulations | C44: in parallel with financial regulations these set out for each organisation the required processes for purchasing goods and services and letting contracts, and for disposing of inventories and assets including authorisations and financial limits, to ensure legal compliance, openness and competition, propriety and probity
B45: MC9: Partnership frameworks | C45: organisations often need to establish formal relationships with others in order to achieve their goals. While this will often be through formal contractual arrangements, partnership agreements can offer an alternative way of binding bodies in shared objectives. Partnership agreements will usefully cover the shared aims and objectives, powers, success criteria, strategic risks, decision making, performance management, review and accountability arrangements, funding arrangements and means of controlling finances, and arrangements in the event of dissolution.
A46: Assurance | B46: formal processes to give assurance to stakeholders about the organisation’s standards and effectiveness, carried out at arm’s length from the operations they examine. The rigour, professionalism and independence of these processes, and of the bodies that carry them out, contribute to public trust and the resilience of the taxpayer relationship.
B47: A1: Internal audit | C47: is an assurance function that provides an independent and objective opinion to the organisation on risk management, control and governance, by evaluating their effectiveness in achieving the organisation’s objectives. It objectively examines, evaluates and reports on the adequacy of the control environment as a contribution to the proper, economic, efficient and effective use of resources, focussing on areas of relatively greater risk. It provides assurance to management and other stakeholders, to prompt cost effective improvements that reduce risk. Auditors can advise management but, as an independent assurance function, internal audit should not be involved in developing or maintaining policies that it later reviews. Thus pre-audit activity can impact on audit independence. In some instances (namely post-Soviet environments) the distinction between inspection and internal audit is blurred: the EU view is that this is determined by the internal auditor, avoiding the assumption of any managerial accountability8, but this sits uneasily with the Anglo-Saxon perspective that internal audit is a tool of top management.
B48: A2: External audit | C48: a review carried out by an independent qualified person of the reliability and regularity of an organisation’s financial arrangements, by analytical review, systems evaluation, compliance and substantive testing. In particular the external auditor gives an opinion on an organisation’s financial statements. An unqualified opinion gives assurance that they are prepared in accordance with legal requirements and a recognised reporting framework and ‘present fairly’ the financial position. This is therefore an important buttress to accountability and can help to build confidence in the organisation’s financial management, while recommendations should lead to improvements in how business is conducted and create pressure for stronger PFM. External auditors can also carry out thematic reviews, examining efficiency, economy and effectiveness or performance reviews, for example on major change or infrastructure programmes
B49: A3: Audit committee | C49: an audit committee is a key component of corporate governance particularly in developed countries. It is a source of assurance about the organisation’s arrangements for managing risk, maintaining an effective control environment, and reporting on financial and non-financial performance. Its purpose, as defined by CIPFA9, is: ‘to provide independent assurance of the adequacy of the risk management framework and the associated control environment, independent scrutiny of the authority’s financial and non-financial performance to the extent that it affects the authority’s exposure to risk and weakens the control environment, and to oversee the financial reporting process.’ Its functions include oversight of internal audit’s activity and effectiveness, of risk management arrangements and the control environment , review of the financial accounts and any external reporting on them. It should promote the significance of audit, seeking assurance that issues arising from internal or external audit reports are being addressed. To be fully effective it should be able to challenge the executive, with a membership that is balanced, objective, independent of mind, and knowledgeable.
B50: A4: Quality accreditation | C50: an independent assurance of the quality of processes or services which results in the award of a formal rating or accreditation. Such reviews may be carried out by service inspectorates, organisations awarding beacon status, or recognised quality assurance standards such as those of the European Quality Foundation. Such assurance mechanisms require a formalised methodology for assessing and validating the activity under review, and an oversight body that underwrites the quality of accreditation.
A51: Scrutiny | B51: scrutiny of PFM processes, outside executive responsibility, can oversee, influence and challenge the allocation of resources and the administration of public sector finances. Scrutiny processes create a demand for transparency and improve accountability. Their influence can help to build pressure for a more open, honest and effective public sector. Scrutiny processes can be formal, such as a Parliamentary Public Accounts Committee, or informal, including civil society groups and the media. Viewed as a whole system, scrutiny processes and bodies are an important part of overall checks and balances and a way of enabling the citizen voice to be heard by executive authority. Citizen and media scrutiny may be extremely important in generating pressure for PFM reform.
B52: SC1: Scrutiny committees | C52: committees that scrutinise aspects of PFM can exist at parliamentary level, such as the legislative scrutiny of the budget law, or Public Accounts Committee scrutiny of external audit reports. Scrutiny committees can also exist at local level. They are a formal way of overseeing budget execution, reviewing performance and pushing for both allocative and operational efficiency. They may also include anti corruption agencies. Scrutiny bodies examine evidence, seek ideas and make recommendations to executive management across financial or service activities. They are part of the wider checks and balances in the PFM system, and help to create a demand for accountability: “A decade of research has concluded that, unless there is strong demand for accountability, most PFM reforms are unlikely to be sustained in the long run”
B53: SC2: Citizen representation and influence | C53: civil society organisations can be influential in generating pressure for reform and in holding executive authority to account, as being a stimulus to improvements in financial management and decision making. Examples in relation to budgets include advocacy and influence on the allocation of resources, creating a demand for budget information and tracking the quality of implementation. Parliament as a whole is intended to represent citizens but other bodies can help to give a voice to a variety of interests
B54: SC3: Media | C54: together with legislatures and citizens, the media help to create an environment of accountability and a demand for information that scrutinises whether policies are being achieved, and can act as a stimulus to improvements. Their role, as well as that of civil society more generally, extends well beyond PFM.
B55: SC4: Whistleblowing | C55: processes that enable individuals or groups to draw formal attention to unacceptable or high risk practices may be particularly significant where the executive performs poorly and other controls and balances in the system are weak.
B56: SC5: Ombudsman | C56: an official, usually appointed by the government or by parliament, who is charged with representing the interests of members of the public. The ombudsman considers and independently investigates complaints by citizens who believe they have received unfair, improper, or unreasonable treatment from government departments or agencies. He or she gives an impartial judgement and can make recommendations for a mediated settlement. The ombudsman may also publish lessons learned or investigate service issues that affect large numbers of people. Making a complaint to an ombudsman is usually free of charge.
A57: Learning & Growth | B57: processes that enable public service organisations, individually and collectively, to reflect and learn from best practice, from partners, mentors and peers and from their own experiences, in order to develop their knowledge and capabilities. Public service organisations can be supported by capacity building initiatives, but they also need to draw inspiration through their roots by involving citizens and service users. Processes for learning and growing enable organisations to become more effective and to achieve better results more efficiently, but also enable them to sustain improvements and take responsibility for their future development. Growing in this context refers to internal growth and not to organisational expansion
B58: LG1: Competency needs analysis | C58: analysis of the skills and knowledge required to meet an organisation’s needs lays the foundation for designing training programmes. The analysis should cover the finance skills of non-financial and devolved managers as well as finance staff, and the leadership, communication and influencing skills of finance experts as well as their technical competence.
B59: LG2: Developing financial literacy | C59: many spending decisions are taken by managers who do not have a financial qualification. Senior managers in leadership positions need to understand, and give weight to, the financial consequences of policy decisions and to direct the financial health of their organisations. Service managers also. need the capabilities to influence the realism of budgets, manage resources within organisational freedoms and disciplines, and know when to seek advice
B60: LG3: Developing institutional capacity in PFM | C60: developing PFM capacity goes beyond individual skills. PFM recognition, routines and expected behaviours may take time to become fully established and embedded within organisations. Understanding and applying concepts, and confidence in dealing with financial issues are relevant for organisations, including Parliament and its officials, as well as for those specifically charged with PFM oversight and scrutiny.
B61: LG4: Developing basic financial competencies | C61: organisations need staff who are competent to carry out basic financial processes and transactions, such as making and recording receipts and payments. Staff need to understand how, and why, to carry out such tasks to the required quality. At a more advanced level, staff with technician competencies can be key to maintaining reliable budgeting, accounting and reporting procedures. Technician level competency can be accredited through examination and also well established relevant experience, and once acquired should be regularly updated. Professional skills can be acquired at different levels, depending on the match to a competency needs analysis, and organisations will need a mix of skills.
B62: LG5: Developing professional competencies | C62: individuals qualified to full professional status should have the skills and motivation to analyse, interpret and advise on financial data. Their skills are relevant to the design of financial management systems and to leadership in their implementation. Professionally qualified staff can apply appropriate techniques across the public sector, but can also take local responsibility for strengthening PFM where they are based, enabling good practice to become embedded and self sustaining. Professional accountancy qualifications can be seen as having two stages: • Initial professional development and qualification: the initial development of skills, knowledge and expertise that has been tested by examination and must be continuously developed in a structured and monitored context. Qualified individuals should adhere to professional values of accuracy, honesty, integrity, objectivity, transparency and reliability. They will be subject to oversight by a professional body that exercises disciplinary powers. • Continuous professional development (CPD): CPD refers to a structured process to broaden skills and keep up to date with professional developments and emerging themes, maintaining and enhancing competencies over time, and meeting the needs of a modern organisation in a changing world. CPD therefore benefits both the individual and their employer. It embraces technical expertise, as well as the leadership, change management, communication and influencing skills that finance staff need to be effective.
B63: LG6: Knowledge sharing and transfer | C63: informal systems for sharing knowledge and experience can increase relevance and practicality, reduce the time taken to learn, avoid repeating lessons learned the hard way through mistakes and avoid repeated buying in of expertise: • Peer improvement networks: the principle of mutuality underlies networking where peers can share success stories, experience and learning, as an accelerated and self directed route to improvement. Peers understand the environment and challenges they each face and can bring a practical appreciation of issues that is directly relevant, recognising that ‘a successful reform program must consider the country’s current circumstances and capacities’. • Communities of practice: allow practitioners to exchange information and experience, and contribute to a collective knowledge base in a loosely structured fashion, often through the internet. • Resources and support: there are many practical ways in which capacity development is supported, such as writing or sharing materials and manuals, study visits, critical friend observation and feedback, coaching and mentoring. • Planned transfer of expertise: where expertise or specialised knowledge needs to be bought in contracts can make specific provision for knowledge transfer, for example by using local systems, local co-workers and ensuring that intellectual property is created and retained by the public sector organisation or published.
B64: LG7: Self assessment (best practice models) | C64: structured models are a tool for improvement, that use a recognised assessment process to enable the organisation to test itself against best practice, to identify areas of strength and opportunities for improvement, and, over time, to measure progress. By demonstrating a commitment to continuous improvement the adoption of such processes also hopes to gain a reputational advantage with stakeholders or funders. Models may address a particular area of business, such as the PEFA assessment, or CIPFA’s Financial Management Model, or take a more holistic view, such as the European Quality Foundation.
B65: LG8: Efficiency and value for money (VFM) processes | C65: • Evaluation: an objective evaluation process using planned criteria, or post implementation review, can support pilot initiatives, can test the effectiveness of implementation, and can provide a platform for dialogue about what works well and what doesn’t, to guide future policy. Its lessons can be fed into future capacity building plans or can inform future activity. • Benchmarking: comparison of costs and activities with other organisations, both the peer group and the best in field, helps to identify scope for improvement. Learning from the practices used by sector leaders accelerates improvement and cost reduction. Organisations need to avoid being defensive about their performance: in the private sector watching the competition is seen as mission critical. • Process review: an approach that maps the stages in an activity from beginning to end, to analyse the value added by each stage in the process. The aim is to redesign the process to remove redundant or low value steps, focussing on meeting the needs of the customer, to improve user satisfaction and to look for opportunities to reduce transaction costs, for example, by reducing duplication, manual handling and automation.
B66: LG9: Research | C66: systematic investigation and evaluation of evidence in order to extend the intellectual capital available and to enhance the effectiveness of current and future practice
B67: LG10: End user/taxpayer/ citizen involvement | C67: the involvement of citizens and service users in public sector financial matters can take a variety of forms, from information (e.g. what services has the budget been spent on), to consultation (what are the citizen’s preferences between services or on the trade-off between taxation and charging), to active engagement, for example, through participatory budgeting. Active involvement can improve the quality of decision making so that resources are targeted more effectively and with better chances of lasting support and impact. It also has wider relevance. A joint CIPFA/DFID technical briefing notes: “As well as giving disadvantaged populations a voice and promoting the interests of marginalised sections of society, participatory budgeting promotes a more democratic and transparent administration of resources and can assist in avoiding corruption and the mishandling of public funds. It encourages public investment towards society’s most pressing needs for the benefit of the greatest number of people.” A strong aim of the multi-country Civil Society Budget Initiative, that supports community based budget monitoring, is budgeting that is ‘pro poor’.

Sheet USAID Classifications
A1: USAID PFM Classification
A2: USAID Guide to Public Financial Management
A4: Budget Planning and Preparation | B4: Overview | C4: Legislative Framework
B5: Budget Planning Process | C5: National Development Plan
C6: MacroEconomic Framework
C7: Fiscal Framework
C8: Macro-Fiscal Framework
C9: Medium-Term Expenditure Framework
B10: Budget Preparation Process | C10: Budget Circular
C11: Budget Calendar
C12: Budget Requests and Negotiation
C13: Types of Budget Approaches
C14: Capital Budget
C15: Public Investment Programs
C16: Budget Approval
C17: Supplemental Budget
B18: Implementing Reform
A20: Budget Execution | B20: Budget Authorization and Apportionment
B21: Acqusition and Verification | C21: Procurement Systems
C22: Requisition Request
C23: Bid Solicitation
C24: Bid Evaluation
C25: Contract Negotiation and Signature
C26: Contract Management
C27: Verification
C28: Project Close-Out
B29: Payment Procedures
B30: Asset Management and Inventory
B31: Payroll
B32: Commitment of Funds
B33: Revenues | C33: Taxes
C34: Tax Administration
B35: Treasury Operations and Cash Management
C36: Treasury Single Account
C37: Debt Management
B38: Implementing Reform
A40: Public Sector Accounting | B40: Basis of Accounting
B41: Chart of Accounts
B42: Implementing Reform
A44: Audit and Evaluation | B44: Internal Audit
B45: External Audit

Sheet NZ-BCM
A1: New Zealand Government Business Capabilities Model
A2: GEC Government Enterprise Capabilities | B2: Government Enterprise Capabilities are not unique to Government. They are needed for any organisation whether it is a corporation, government, non-government, or not-for-profit corporations. They are also known as corporate capabilities, or even back-office capabilities. Most organisations like a food franchise or an internet content provider are implementing the same enabling business capabilities like Human Resources, and Finance. Enterprise capabilities are ideal candidates for shared capabilities, from people and process capabilities realised by community of practice groups, through a shared digital capabilities and potentially through a single implementation of the capability being used by all that brings people, process, information, and technology capabilities together. Caution is needed as while a single implementation of an enterprise capability may appear to be most efficient, it may also be less agile. The various factors have to be appropriately considered in each case while any candidate shared capability options are explored. The processes to support enterprise capabilities are well understood and are largely standardised and the people skills are readily available. As a result, when organisations merge, it is usually enterprise capabilities that are consolidated first. The intention is to refine the government enterprise capabilities and identify those capabilities where there is maximum system benefit to develop system capability. For example, there are common process models for several areas within this capability domain.
B3: GEC01 Strategy and Planning | C3: There are two basic questions to ask of management: are we doing things right, and are we doing the right things? Operational management focuses on doing things right, and many tools have been developed to improve this (e.g. TQM, Six Sigma, business process reengineering etc.), including many maturity models. Strategic Portfolio management answers the second question are we doing the right things. In any organisation, it is the strategy, driven from the vision of the leadership that defines what the right things are. Process improvements alone cannot guarantee that an organisation will be successful, or that an agency will achieve its mission. These two aspects of management – strategic and operational – complement each other, so both must be assessed to determine the organisation's total management capabilities and are bridged with the Programme and Project Management capability. An organisation’s strategy should be: - Valuable: An organisation’s strategy needs to effectively allocate resources to the best investment opportunities, drive performance and raise expectations internally and externally, improve the organisation’s outcomes and add value. - Enduring: In developing a strategy, organisations should consider short-term and long-term cycles and macro-trends while ensuring their plan is resilient and adaptive. - Forward-looking: A solid strategy appropriately anticipates risk, uncertainty and optionality. - Actionable: A high performing organisation ensures their strategy is both intuitive and realistic. It should be easy to communicate the strategy internally and externally and provide an approach that can be acted on by all business units at all levels
C4: GEC01.01 Business Strategy Development | D4: The Business Strategy Development capability focusses on the development of goals, objectives, strategies and tactics based on factual data. The first step in the development of any business strategy is the determination of the goals. For government entities these will be All-of-Government, sector and agency goals. This will set the stage for developing measures and specific actions that the organisation will need to take to achieve these goals. For instance, the goal might be to "Be more customer-centric" and to "Improve customer experience". Once a goal has been established and the actions needed are clear, information is gathered so that the decisions are based on solid facts and data. The situation analysis involves a review of information internal as well as external to the agency. A SWOT analysis needs to be executed to identify the agency's strengths and weaknesses, which are internal; and opportunities and threats, which are external. Based on that information and by prioritising these items, the organisation gets a better sense of the most important areas to focus on. Objectives are the measurable element of the strategy. Objectives indicate, specifically, what outcomes are desired. While goals set a broad direction ("Improve customer experience"), objectives will provide the detail that ensures the team knows when it achieves success. Strategies and tactics will indicate how and what the organisation will need to do to achieve its goals and objectives. Strategies provide general guidance, such as "engage in social media activities," while tactics outline specific tasks that will be done, such as "set up a LinkedIn discussion group".
C5: GEC01.02 Strategic Roadmap Development | D5: Strategic Roadmaps are planning tools that identify strategic goals and pathways for improving the overall business and to achieve the strategic goals of the agency. The emphasis of the roadmap development capability is on activities and decisions, as opposed to business planning. The outcome of the development process will be roadmaps that will identify: - Actionable steps necessary to achieve the desired outcomes. - Interdependencies among steps. - Alternative routes that will optimise opportunities or minimise risks. When completed, the roadmaps will be used: - As a communication tool to inform key stakeholders on the potential for the agency, sector, and Government and their customers. - To identify the key issues that currently affects the organisation and its ability to improve. - To identify what actionable steps are required to achieve the desired goals and objectives, and within this, which actions and steps have the highest priority and which will give the greatest benefit relative to their cost. - To identify the intermediate steps and interdependencies within the organisation and their business partners.
C6: GEC01.03 Corporate Governance | D6: Corporate governance refers to the mechanisms, processes and relations by which the agency is controlled and directed. Governance structures and principles identify the distribution of rights and responsibilities among different participants in the agency (such as the board of directors, managers, shareholders, creditors, auditors, regulators, and other stakeholders) and include the rules and procedures for making decisions in corporate affairs. Corporate governance includes the processes through which the agency's objectives are set and pursued in the context of the social, regulatory and economic environments. Governance mechanisms include monitoring the actions, policies, practices, and decisions of the leaders.
C7: GEC01.04 Outcome Management | D7: Outcome Management is the strategic approach to ensure that initiatives are designed around departmental and government outcomes and that the intended outcomes are achieved. Just as project management deals with the processes necessary to deliver a capability and/or product within a pre-established time frame and budget, Outcome Management adds value to the organisation increasing value is achieved through effective benefits realisation.
C8: GEC01.05 Business Performance Management | D8: Business Performance Management is a set of management and analytic processes that enables management of performance to achieve one or more pre-selected goals. Business Performance Management has three main activities: - Selection of the goals. - Consolidation of measurement information relevant to the agency’s progress against these goals. - Interventions made by managers in light of this information with a view to improve future performance against these goals.
B9: GEC02 Change Management | C9: Change Management affects the activities involved in managing changes to how the government conducts its business in providing government services to individuals, businesses and other organisations including managing the resulting changes to business requirements, as well as their impacts on stakeholders of the government business solutions.
C10: GEC02.01 Transformation Strategy Development | D10: Developing a transformation strategy includes a comprehensive assessment of current and new processes, technologies, people, and resources. Most transformation strategies are about responding to changes that new technologies cause in our daily lives, individual businesses and organisations, industries and various segments of society. These changes are not brought upon us by the technologies themselves but by people. The ways people use and experience new technologies can have very unexpected consequences. It is important for the success of transformation strategy to put people and processes above technology.
C11: GEC02.02 Change Sponsorship | D11: Change management requires sponsorship by senior leaders in the organisation. Sponsorship involves active and visible participation by senior business leaders throughout the change management process. Plans and roadmaps for sponsorship activities are needed.
C12: GEC02.03 Transformation Planning | D12: Transformation Planning starts at the top of the organisation with strategic goals, objectives, and planning. All strategic decisions have an impact on the organisation and the organisation will have to adapt to achieve those strategic goals and objectives. Transformation Planning is the capability to plan the different changes within the organisation and to make sure they are all aligns with each other so the predicted outcomes are achieved with as less destructive impact to the whole organisation.
C13: GEC02.04 Transformation Governance | D13: Transformation Governance is the capability to ensure that the organisational and transformation principles are well applied to design and implementation of the transformation. It also ensures that the organisation meet business and technology objectives and standards. Transformation Governance enables effective alignment of business and technology, manages risk by reducing probability of failures in transformation and incorporates elements of cost effectiveness and value.
C14: GEC02.05 Change Resistance Management | D14: Change Resistance management is the capability to manage employee resistance to change. A transformation programme needs to identify, understand, and manage resistance to change.
C15: GEC02.06 Benefit Management | D15: Benefits management is the capability to increase the successful delivery of quantifiable and meaningful business benefits to an organisation during change. It focuses on how business areas will benefit from change and provides a framework for identifying, planning, measuring and actively managing these benefits.
C16: GEC02.07 Change Readiness Assessment | D16: Change Readiness assessments cover a wide range of areas across the organisation from sponsors to organisational culture in order to determine how ready the organisation is for change, and help identify area and factors that can affect the success of the change.
C17: GEC02.08 Programme and Project Management | D17: Programme management is the capability to manage several related projects and oversee the implementation of each of those projects into one overall group of outcomes to achieve the organisation's goals and objectives. Project management is the capability to manage people and other resources to deliver the project outcome.
C18: GEC02.09 Requirements Management | D18: Requirement management is the capability to document, analyse, trace, prioritise, and agree on requirements for an initiative and communicate with the relevant stakeholders. Requirement management covers functional and non-function requirements, high level through to more detailed requirements.
C19: GEC02.10 Change Communication | D19: Change communication is the capability to build awareness of the need for change and to create the desire for change. At each step of the change process the right messages need to be delivered at the right time - this requires careful analysis of the audience and the messages, and a communication plan.
C20: GEC02.11 Change Coaching and Training | D20: Change coaching and Training is the capability to gain support from the direct supervisors and managers of employees and provide training in order for employees to be able to implement the change.
B21: GEC03 Financial Management | C21: Financial Management means planning, organising, directing and controlling the financial activities such as procurement and utilisation of funds of the organisation. It means applying general management principles to financial resources. The scope of Financial Management includes: - Investment decisions - Includes investment in fixed assets and current assets. - Financial decisions - Relates to the raising of finance from various resources which will depend upon decision on type of source, period of financing, cost of financing and the returns. - Dividend decision - Decision making with regards to the net profit distribution. Net profits are generally divided into two: dividend for shareholders and retained profits. The financial management is generally concerned with procurement, allocation and control of financial resources. The objectives include: - Ensuring regular and adequate supply of funds. - Ensuring adequate returns to the shareholders which will depend upon the earning capacity, market price of the share, expectations of the shareholders. - Ensuring optimum funds utilisation. Once the funds are procured, they should be utilised in maximum possible way at least cost. - Ensuring safety on investment, i.e., funds should be invested in safe ventures so that adequate rate of return can be achieved. - Planning a capital structure that is a fair composition of the capital so that a balance is maintained between debt and equity capital. The functions within Financial Management include: - Estimating capital requirements: A finance manager has to make estimation with regards to capital requirements of the company. This will depend upon expected costs, profits, future programmes, and policies estimating in an adequate manner which increases earning capacity of the enterprise. - Determination capital composition: Once the estimation has been made, the capital structure has to be decided. This involves short- term and long- term debt equity analysis. This will depend upon the proportion of equity capital an organisation is possessing and additional funds which have to be raised from outside parties. - Choosing sources of funds: For additional funds to be procured, a company has many choices like-Issue of shares and debentures, loans to be taken from banks and financial institutions. - Choosing factors that will depend on relative merits and demerits of each source and period of financing. - Investing funds: The finance manager has to decide to allocate funds into profitable ventures so that there is safety on investment and regular returns is possible. - Disposing surplus: The net profits decision have to be made by the finance manager. This can be done in two ways: - Dividing declaration: It includes identifying the rate of dividends and other benefits like bonus. - Retaining profits: The volume has to be decided which will depend upon expansion, innovation, and diversification plans of the organisation. - Managing cash: Finance manager has to make decisions with regards to cash management. Cash is required for many purposes like payment of wages and salaries, payment of electricity and water bills, payment to creditors, meeting current liabilities, maintenance of enough stock, purchase of raw materials, etc. - Financial controls: The finance manager has not only to plan, procure and utilize the funds but he also has to exercise control over finances. This can be done through many techniques like ratio analysis, financial forecasting, cost and profit control, etc.
C22: GEC03.01 Financial Strategy Development | D22: Developing a financing strategy includes a comprehensive assessment of potential new financing options from concessional and non-concessional sources, as well as possible grant inflows, focusing on how to best mobilise the highest quality financing to support priorities and ensure debt sustainability for the organisation. The basis of resource need to be concessional, conditional, predictable, flexible, and focussed on organisational priorities and other policy and procedural criteria.
C23: GEC03.02 Financial Forecasting and Planning | D23: Financial Forecasting and Planning starts at the top of the organisation with strategic planning. Since strategic decisions have financial implications, the budgeting process is closely linked to the strategic planning process. Financial Planning is a continuous process of directing and allocating financial resources to meet strategic goals and objectives in order to add value to the organisation. The output from financial planning takes the form of budgets. In order to develop budgets, a forecast needs to be undertaken to see what drives much of the financial activity.
C24: GEC03.03 Financial Governance | D24: Financial Governance is the combination of institutions, rules, and norms that structure governance in these policy areas. Fiscal governance focusses on directing and approving how budgetary policy is planned, approved, carried out and monitored, generally involving more than the agency. The core of financial governance regulations is the requirement that all financial processes are managed according to a stringent set of rules and regulations, backed by accurate reporting capabilities. This management and recording of internal controls, to work toward compliance, can be set down in a concise and controlled manner and can save the organisation significant time and money. Financial governance is important for good overall governance because the consequences of failure can be so devastating for the organisation that no matter how good the rest of area's governance may be financial failure can bring it undone. There are three keys to effective financial governance: - Creating a policy that guides the CEO in developing the business plan including the budget or financial plan – this relates primarily to the operating revenue and costs of the business as well as the cash flow management of the organisation. - Creating a policy that establishes the basis for the organisation’s wellbeing – this relates to the management of the assets and liabilities of the business. - Monitoring processes that provide the organisation with sufficient financial information to be satisfied that the finances are being appropriately managed towards the achievement of both the short and long term goals. This includes establishing key performance indicators and benchmarks for performance evaluation and a framework that provides the board, management and staff with a reporting system in an accurate and timely manner.
C25: GEC03.04 Financial Control | D25: Financial Control is the capability to track performance and evaluate progress toward the financial goals of the organisation. Financial controls evaluate how well the organisation is following the strategic plans and how valid the strategic decisions were in the first place. Financial controls include tracking progress and evaluating results. During strategic planning, management defines measurable objectives for operations. Financial controls report on these objectives and to what extent they have been met. During the reporting period, managers can impose corrective action if necessary and at the end of the reporting period, the results form part of the overall evaluation of the success of the strategic plan.
C26: GEC03.05 Financial Auditing | D26: Financial Auditing is the capability to conduct an audit to provide an opinion whether financial statements are stated in accordance with specified criteria. Normally, the criteria are international accounting standards, although auditors may conduct audits of financial statements prepared using the cash basis or some other basis of accounting appropriate for the organisation. In providing an opinion whether financial statements are fairly stated in accordance with accounting standards, the auditor gathers evidence to determine whether the statements contain material errors or other misstatements. The audit opinion is intended to provide reasonable assurance that the financial statements are presented fairly, in all material respects, and/or give a true and fair view in accordance with the financial reporting framework. The purpose of an audit is to provide an objective independent examination of the financial statements, which increases the value and credibility of the financial statements produced by management, thus increase user confidence in the financial statement, reduce stakeholder risk and consequently reduce the cost of capital of the preparer of the financial statements.
C27: GEC03.06 Financial Operations | D27: Financial Operations is the capability of the day-to day operations of accounting services, financial reporting, payroll, loan collections, taxes, and other financial services.
B28: GEC04 Enterprise Risk Management | C28: Enterprise Risk Management (ERM) is the capability of agencies to manage their risks through their different business units and functions that identify and manage particular risks. Each risk function varies in capability and how it coordinates with other risk functions. A central goal and challenge of ERM is to improve this capability and coordination, while integrating the output to provide a unified picture of risk for stakeholders and improving the organisation's ability to manage the risks effectively. The primary risk functions that should participate in an ERM program are: - Strategic planning - identifies external threats along with strategic initiatives to address them. - Marketing - understands the customer to ensure product/service alignment with customer requirements. - Compliance and Ethics - monitors compliance with code of conduct and directs fraud investigations. - Accounting and Financial compliance - identifies financial reporting risks. - Policy - manages legislation and analyses emerging legal trends that may impact the agency. - Insurance - ensures the proper insurance coverage for the organisation. - Treasury - ensures cash is sufficient to meet business needs, while managing risk related to commodity pricing or foreign exchange. - Operational Quality Assurance - verifies operational output is within tolerances. - Operations management - ensures the business runs day-to-day and that related barriers are surfaced for resolution. - Customer service - ensures customer complaints are handled promptly and root causes are reported to operations for resolution. - Internal audit - evaluates the effectiveness of each of the above risk functions and recommends improvements. Common challenges in ERM implementation - Identify executive sponsorship for ERM. - Establish a common risk language or taxonomy. - Describe business unit’s risk appetite - risks they are willing to take and risk they are not willing to take. - Identify and describe the risks in a risk catalogue. - Implement a methodology to prioritise risks within and across business units and functions. - Establish a risk steering group to authorise and coordinate activities around risk management. - Establish ownership for particular risks and responses. - Demonstrate cost-benefit of the risk management effort. - Develop an action plan to ensure the risks are appropriately managed. - Develop consolidated reporting for the various stakeholders. - Monitor the results of the actions taken to mitigate the risks. - Ensure efficient risk coverage by internal auditors, consulting teams, and other evaluating entities. - Ensure a secure working environment for contractors, partners, and remote employees.
C29: GEC04.01 Strategic Risk Assessment | D29: Strategic Risk Assessment is the capability to systematically and continually assessing significant risks facing the organisation. Conducting an initial assessment is a valuable activity for senior management and the board of directors. Current thought leadership on corporate governance and board responsibilities is virtually unanimous that a key board responsibility is to understand the organisation’s strategies and associated risks and to ensure that management’s risk management practices are appropriate.
C30: GEC04.02 Risk Portfolio Management | D30: Risk Portfolio Management is the capability of making decisions about risks, investments and policy, matching investments to risk objectives, asset allocation for individuals and institutions, and balancing risk against performance. Risk Portfolio management is all about strengths, weaknesses, opportunities and threats for the organisation.
C31: GEC04.03 Business Impact Analysis | D31: Business Impact Analysis is the capability to determine the relative importance or criticality of business functions, operations, supplies, systems, relationships etc. that are required to achieve the organisation's operational objectives. It drives the priorities, planning, preparations and other business continuity management activities.
C32: GEC04.04 Risk Improve Effectiveness Planning | D32: Risk Improve Effectiveness Planning is the capability of planning a systematic way of finding how effective an organisation’s current approach to managing risk is. It considers the intentions of the organisation, how they are expressed and communicated and also what happens in practice. This leads to a realistic improvement program plan for the organisation’s risk management framework and each application of the risk management process. The plan has five major steps: Prepare, Elicit and verify, analyse gaps and evaluate, gain ownership and plan, and report to the oversight committee.
C33: GEC04.05 Risk Mitigation Planning | D33: Risk Mitigation Planning is the process of developing options and actions to enhance opportunities and reduce threats to the organisation's objectives.
C34: GEC04.06 Business Continuity Planning | D34: Business Continuity Planning is the capability that encompasses a loosely defined set of planning, preparatory and related activities which are intended to ensure that the organisation’s critical functions will either continue to operate despite serious incidents or disasters that might otherwise have interrupted them, or will be recovered to an operational state within a reasonably short period. Business continuity includes three key elements: - Resilience: critical business functions and the supporting infrastructure are designed and engineered in such a way that they are materially unaffected by most disruptions, for example through the use of redundancy and spare capacity. - Recovery: arrangements are made to recover or restore critical and less critical functions that fail for some reason. - Contingency: the organisation establishes a generalised capability and readiness to cope effectively with whatever major incidents and disasters occur, including those that were not, and perhaps could not have been, foreseen. Contingency preparations constitute a last-resort response if resilience and recovery arrangements should prove inadequate in practice. Some examples of risks: - Single points of failure with the Telco link between NZ and Australia. How will Treasury maintain balance of payments account if it cannot access the Internet via this link or a broken down ICT infrastructure as with Christchurch disaster. - How does petrol and oil get distributed to power the generators if there are poor or broken roads as a result of earthquakes? - How do people access the Government resources that are on their websites if they cannot access it?
C35: GEC04.07 Risk Management Governance | D35: Risk Management Governance refers to the institutions, rules conventions, processes and mechanisms by which decisions about risks are taken and implemented. It can be both normative and positive, because it analyses and formulates risk management strategies. Risk Management Governance goes beyond traditional risk analysis to include the involvement and participation of various stakeholders as well as considerations of the broader legal, political, economic and social contexts in which a risk is evaluated and managed. The scope of Risk Management Governance encompasses public health and safety, the environment, old and new technologies, security, finance, and many others.
C36: GEC04.08 Risk Intervention Monitoring | D36: Risk Intervention Monitoring is the capability to monitor the process and targeted intervention to: - Identify the organisation's risks and develop a risk library. - Identify and prioritise “risks that matter” to the organisation. - Develop mitigation plans for ”risks that matter”. - Develop a risk monitoring process.
C37: GEC04.09 Security Control | D37: Security Control is the capability to significantly reduce security vulnerabilities. Today’s connected environment introduces various ethical, financial and regulatory pressures to protect the privacy of individuals and the information assets of organisations from internal and external threats and unauthorised access. Successful attacks, whether deliberate or inadvertent, are an increasingly more costly and damaging, both to the organisation and its customers. To meet these challenges, Security Control is a fundamental strategic driver of the business. Security Control defines a conceptual, physical and procedural model of best practices for end-to-end enterprise security. This includes: - The approach for determining and setting the baseline or threshold of acceptable risk to the business. - Standard methods for ascertaining appropriate classification of information assets. - A base set of policies, processes, standards, and procedures for achieving and maintaining an integrated defence of the organisation's information resources and assets. - The security functions, roles and responsibilities appropriate for each member of the organisation. - The essential skills and knowledge needed to perform information security effectively.
C38: GEC04.10 Mitigation Improvement Management | D38: Mitigation Improvement Management is the capability to continuously improve the anticipation of risks, threats, and disasters. Developmental considerations play a key role in contributing to the mitigation and preparation of an organisation to effectively confront those threats and disasters. As a security breach or disaster occurs, risk management, become involved in the immediate response and long-term recovery phases. The four risk management phases illustrated here do not occur in isolation or in this precise order. The phases overlap and the length of each phase greatly depends on the severity of the breach or disaster. - Mitigation - Minimizing the effects of breach or disaster. - Preparedness - Planning how to respond. - Response - Efforts to minimise the hazards created by a breach or disaster. - Recovery - Returning to normal.
C39: GEC04.11 Risk Mitigation Development | D39: Risk Mitigation Development is the capability to develop the processes of executing risk mitigation actions. Risk mitigation progress monitoring includes tracking identified risks, identifying new risks, and evaluating risk process effectiveness throughout the project.
C40: GEC04.12 Risk Intervention Development | D40: Risk Intervention Development is the capability to create a strong risk culture based on the empowerment of the business. It creates a dedicated risk-culture function within the risk organisation by: - Creating awareness and a common language and identifying improvement levers and implement them, for example, by rolling out a semi-annual or quarterly risk-culture self-assessment. - Launching a program to assess and transform current risk capabilities with the support of a dedicated change team. - Defining specific actions, owners, and milestones, and establishing an ongoing method of monitoring the risk-culture transformation.
C41: GEC04.13 Risk Management Operations | D41: Risk Management Operations is the capability of the day-to day operations of risk management data protection, risk event operations, implement risk communication channels, etc.
B42: GEC05 Communications | C42: The Communications capability provides strategic communications consultation, media relations efforts, strategic digital communication and planning services on behalf of the organisation.
C43: GEC05.01 Internal Communication Strategy Development | D43: Internal Communications serves as a channel or network that links parts of the organisation together. Much of the communication that occurs in an organisation is informal and uncontrollable, other communications are structured and intentional and carefully planned. An internal customer insight mechanism needs to be in place for internal strategy development. The development of the internal communications strategy is to identify: - What are the goals, ambitions and it strategic aspirations for the future? - What do the people in the organisation need to think, feel and do in order to make those goals a reality? - Where are employees now? What needs to change in their current perceptions, attitudes, or access to basic information? - What’s the role of the internal communication function in helping close the gap of what we want for the future, and what we’ve got today? - What are the roles and responsibilities of leaders, managers, employees and communication professionals? - What are the communication activities we’re going to need – and who will be responsible for what? - What resource levels do we need?
C44: GEC05.02 External Communication Strategy Development | D44: External Communications Strategy Development refers to policy-making and guidance for consistent information activity between organisations. It includes the organisation’s efforts to understand and engage with key audiences to create, strengthen, or preserve conditions favourable for the advancement of organisation’s interests, policies, and objectives through the use of coordinated programmes, plans, themes, messages, and products.
